Workbook

Sheet README
A1: Month-End Close & Compliance Pack
A2: Portfolio piece: Financial Accountant capability (retail environment)
A4: IMPORTANT | B4: All figures are SIMULATED and illustrative at a scale loosely comparable to a mid-sized ASX specialty retailer. They are NOT Adairs' reported results and no internal company data is used. Replace the inputs with figures from the published Annual Report / half-year results if you want the pack anchored to reported numbers.
A6: Purpose | B6: Demonstrates a full monthly close: trial balance, balance sheet reconciliations with ageing and sign-off, P&L flux analysis, a close calendar with owners and due dates, and a control sheet that proves everything ties. BAS/IAS and FBT workings are built and linked to the GL; payroll oversight, a driver-based rolling forecast with scenario switch, and a Python bank reconciliation automation are also built.
A8: Tab | B8: What it does
A9: Control | B9: One-page proof the close ties: TB balances, journals net to zero, P&L agrees to TB, all reconciliations reconciled. Overall PASS / REVIEW flag.
A10: Inputs | B10: Period, preparer, GST rate, ageing and flux thresholds. Every assumption lives here.
A11: CoA | B11: Chart of accounts with type, statement, normal balance, reconciliation owner, plus a change-control log.
A12: TB | B12: Simulated trial balance (prior month closing, closing, month movement, budget, prior year). Debits positive, credits negative.
A13: Close_Calendar | B13: Day-by-day close checklist with working-day due dates, owners, status dropdowns and completion %.
A14: Rec_Summary | B14: Dashboard of all balance sheet reconciliations: GL vs source, difference, journals required, aged items.
A15: Rec_Bank ... Rec_Payroll | B15: Eight reconciliation tabs on one standard template (GL, source balance, timing items vs GL adjustments, ageing, sign-off).
A16: Variance | B16: Month P&L actual vs budget vs prior year, favourable/(unfavourable), automatic 'Explain' flags, commentary column.
A17: BAS_IAS | B17: Monthly BAS (G1, G2, G3, G10, G11, 1A, 1B, W1, W2) built from TB data, reconciled back to GL GST and PAYG accounts with every difference explained, plus IAS workings.
... A22: Colour legend | B22: Blue = hardcoded input / simulated data
B23: Black = formula on the same sheet
B24: Green = link to another sheet
B25: Yellow fill = cell to complete (commentary, sign-off)
A27: Sign convention | B27: TB: debits positive, credits negative. Reconciliation tabs show liabilities as positive (sign factor on each tab).
A28: Reconciliation logic | B28: Difference = (GL balance + GL adjustments) - (source balance + timing items). Timing items clear on their own next period; GL adjustments need a journal. Items older than the ageing threshold are flagged.

Sheet Control
A1: Close Control Sheet
A2: Every check below must show PASS before the period is locked
A3: Period end: | C3: =Inputs!$C$5 -> 46295
A5: # | B5: Control check | C5: Value | D5: Result
A6: 1 | B6: Trial balance (closing) sums to nil | C6: =ROUND(TB!F47,0) -> 0 | D6: =IF(C6=0,"PASS","FAIL") -> PASS
A7: 2 | B7: Trial balance (prior month) sums to nil | C7: =ROUND(TB!E47,0) -> 0 | D7: =IF(C7=0,"PASS","FAIL") -> PASS
A8: 3 | B8: Month movements net to nil (journals balance) | C8: =ROUND(TB!G47,0) -> 0 | D8: =IF(C8=0,"PASS","FAIL") -> PASS
A9: 4 | B9: P&L: month NPBT per Variance agrees to TB movement | C9: =ROUND(Variance!C30+SUMIF(TB!$D$6:$D$46,"PL",TB!$G$6:$G$46),0) -> 0 | D9: =IF(C9=0,"PASS","FAIL") -> PASS
A10: 5 | B10: All balance sheet reconciliations reconciled (count not reconciled) | C10: =COUNTIF(Rec_Summary!G6:G13,"<>RECONCILED") -> 0 | D10: =IF(C10=0,"PASS","FAIL") -> PASS
A11: 6 | B11: Total unreconciled difference across reconciliations | C11: =Rec_Summary!F14 -> 0 | D11: =IF(ABS(C11)<=Inputs!$C$12,"PASS","FAIL") -> PASS
A12: 7 | B12: BAS GST and PAYG-W agree to GL after documented items (unexplained difference) | C12: =ROUND(BAS_IAS!H33,0) -> 0 | D12: =IF(C12=0,"PASS","FAIL") -> PASS
A13: 8 | B13: FBT summary agrees to schedule total (difference) | C13: =ROUND(FBT!E38,0) -> 0 | D13: =IF(C13=0,"PASS","FAIL") -> PASS
A14: 9 | B14: Fixed asset register agrees to GL, P&L depreciation and BAS capex (sum of differences) | C14: =ROUND(FA_Register!F31,0) -> 0 | D14: =IF(C14=0,"PASS","FAIL") -> PASS
A15: 10 | B15: Reconciling items older than ageing threshold (count) | C15: =Rec_Summary!I14 -> 1 | D15: =IF(C15=0,"PASS","REVIEW") -> REVIEW
A16: 11 | B16: Close calendar tasks completed | C16: =Close_Calendar!B3 -> 0.375 | D16: =IF(C16=1,"PASS","IN PROGRESS") -> IN PROGRESS
B18: Overall status (hard controls 1-9) | D18: =IF(AND(D6="PASS",D7="PASS",D8="PASS",D9="PASS",D10="PASS",D11="PASS",D12="PASS",D13="PASS",D14="PASS"),"ALL PASS","REVIEW") -> ALL PASS
B19: Checks 10-11 are workflow indicators: aged items and close progress. They do not fail the hard controls.

Sheet Inputs
A1: Inputs & Assumptions
A2: Blue cells are inputs; everything else in the workbook reads from here
B3: Entity | C3: Specialty retailer (simulated, Adairs-style) | D3: Illustrative entity; not Adairs reported data
B4: Reporting period | C4: September 2026 (Q1 FY27) | D4: Label only
B5: Period end date | C5: 46295 | D5: Drives close calendar due dates and ageing
B6: Prepared by | C6: Bhagyashree Amblimath | D6: Preparer on all reconciliations
B7: Reviewed by | C7: Financial Controller (simulated) | D7: Reviewer sign-off is left blank for completion
B8: GST rate | C8: 0.1 | D8: Australian GST rate
B9: Reconciling-item ageing threshold (days) | C9: 30 | D9: Items older than this are flagged 'Aged'
B10: Flux threshold ($) | C10: 100000 | D10: Variance must exceed this AND the % threshold to flag 'Explain'
B11: Flux threshold (%) | C11: 0.05 | D11: As above
B12: Reconciliation tolerance ($) | C12: 1 | D12: Differences under this show as RECONCILED

Sheet CoA
A1: Chart of Accounts
A2: Simulated retail chart of accounts with reconciliation ownership
A5: Code | B5: Account name | C5: Type | D5: Statement | E5: Normal bal. | F5: Reconciled in | G5: Owner
A6: 1000 | B6: Cash at bank - operating | C6: Asset | D6: BS | E6: Dr | F6: Rec_Bank | G6: Treasury
A7: 1010 | B7: Store floats and cash on hand | C7: Asset | D7: BS | E7: Dr | G7: Retail Ops
A8: 1100 | B8: Trade debtors | C8: Asset | D8: BS | E8: Dr | F8: Rec_AR | G8: AR
A9: 1150 | B9: Other receivables | C9: Asset | D9: BS | E9: Dr | G9: AR
A10: 1200 | B10: Inventory - finished goods | C10: Asset | D10: BS | E10: Dr | F10: Rec_Inventory | G10: Supply Chain Finance
A11: 1210 | B11: Inventory in transit | C11: Asset | D11: BS | E11: Dr | F11: Rec_Inventory | G11: Supply Chain Finance
A12: 1300 | B12: Prepayments | C12: Asset | D12: BS | E12: Dr | F12: Rec_Prepayments | G12: Financial Accountant
A13: 1500 | B13: Store fit-out - cost | C13: Asset | D13: BS | E13: Dr | F13: FA_Register | G13: Financial Accountant
A14: 1505 | B14: IT equipment - cost | C14: Asset | D14: BS | E14: Dr | F14: FA_Register | G14: Financial Accountant
A15: 1510 | B15: Store fit-out - accumulated depreciation | C15: Asset | D15: BS | E15: Cr | F15: FA_Register | G15: Financial Accountant
A16: 1515 | B16: IT equipment - accumulated depreciation | C16: Asset | D16: BS | E16: Cr | F16: FA_Register | G16: Financial Accountant
A17: 2000 | B17: Trade creditors | C17: Liability | D17: BS | E17: Cr | F17: Rec_AP | G17: AP
A18: 2010 | B18: Accrued expenses | C18: Liability | D18: BS | E18: Cr | F18: Rec_Accruals | G18: Financial Accountant
A19: 2020 | B19: Goods received not invoiced (GRNI) | C19: Liability | D19: BS | E19: Cr | F19: Rec_Accruals | G19: Supply Chain Finance
A20: 2100 | B20: PAYG withholding payable | C20: Liability | D20: BS | E20: Cr | F20: Rec_Payroll | G20: Payroll
A21: 2110 | B21: Superannuation payable | C21: Liability | D21: BS | E21: Cr | F21: Rec_Payroll | G21: Payroll
A22: 2120 | B22: Accrued wages | C22: Liability | D22: BS | E22: Cr | F22: Rec_Payroll | G22: Payroll
A23: 2130 | B23: Provision - annual leave | C23: Liability | D23: BS | E23: Cr | G23: Payroll
A24: 2300 | B24: GST collected | C24: Liability | D24: BS | E24: Cr | F24: Rec_GST | G24: Financial Accountant
A25: 2310 | B25: GST paid (input tax credits) | C25: Asset | D25: BS | E25: Dr | F25: Rec_GST | G25: Financial Accountant
A26: 2400 | B26: Gift card liability | C26: Liability | D26: BS | E26: Cr | G26: Retail Ops
A27: 2500 | B27: Borrowings | C27: Liability | D27: BS | E27: Cr | G27: Treasury
A28: 3000 | B28: Share capital | C28: Equity | D28: BS | E28: Cr | G28: Financial Controller
A29: 3100 | B29: Retained earnings - opening | C29: Equity | D29: BS | E29: Cr | G29: Financial Controller
A30: 4000 | B30: Sales - stores | C30: Revenue | D30: PL | E30: Cr | G30: Financial Accountant
A31: 4010 | B31: Sales - online | C31: Revenue | D31: PL | E31: Cr | G31: Financial Accountant
A32: 4900 | B32: Sales returns and discounts | C32: Revenue | D32: PL | E32: Dr | G32: Financial Accountant
A33: 5000 | B33: Cost of goods sold | C33: COGS | D33: PL | E33: Dr | G33: Supply Chain Finance
A34: 5010 | B34: Freight inwards | C34: COGS | D34: PL | E34: Dr | G34: Supply Chain Finance
A35: 5020 | B35: Inventory shrinkage and provisions | C35: COGS | D35: PL | E35: Dr | G35: Supply Chain Finance
A36: 6000 | B36: Wages and salaries - stores | C36: Expense | D36: PL | E36: Dr | G36: Payroll
A37: 6010 | B37: Wages and salaries - head office | C37: Expense | D37: PL | E37: Dr | G37: Payroll
... A46: 7000 | B46: Interest expense | C46: Expense | D46: PL | E46: Dr | G46: Treasury
A49: Chart of accounts change log (illustrative entries)
A50: Date | B50: Change | C50: Requested by | D50: Approved by
A51: 46217 | B51: Added 2020 GRNI to separate accrued inventory from general accruals | C51: Supply Chain Finance | D51: Financial Controller
A52: 46237 | B52: Split fit-out and IT equipment into separate cost / accumulated depreciation pairs | C52: Financial Accountant | D52: Financial Controller

Sheet TB
A1: Trial Balance
A2: Debits positive, credits negative. P&L closing balances are year-to-date; movement = this month's activity
A3: Period end: | B3: =Inputs!$C$5 -> 46295
A5: Code | B5: Account name | C5: Type | D5: Statement | E5: Prior month closing ($) | F5: Closing balance ($) | G5: Month movement ($) | H5: Month budget ($) | I5: Prior-year month ($)
A6: 1000 | B6: =INDEX(CoA!$B$6:$B$46,MATCH($A6,CoA!$A$6:$A$46,0)) -> Cash at bank - operating | C6: =INDEX(CoA!$C$6:$C$46,MATCH($A6,CoA!$A$6:$A$46,0)) -> Asset | D6: =INDEX(CoA!$D$6:$D$46,MATCH($A6,CoA!$A$6:$A$46,0)) -> BS | E6: 6500000 | F6: 7190000 | G6: =F6-E6 -> 690000
A7: 1010 | B7: =INDEX(CoA!$B$6:$B$46,MATCH($A7,CoA!$A$6:$A$46,0)) -> Store floats and cash on hand | C7: =INDEX(CoA!$C$6:$C$46,MATCH($A7,CoA!$A$6:$A$46,0)) -> Asset | D7: =INDEX(CoA!$D$6:$D$46,MATCH($A7,CoA!$A$6:$A$46,0)) -> BS | E7: 400000 | F7: 410000 | G7: =F7-E7 -> 10000
A8: 1100 | B8: =INDEX(CoA!$B$6:$B$46,MATCH($A8,CoA!$A$6:$A$46,0)) -> Trade debtors | C8: =INDEX(CoA!$C$6:$C$46,MATCH($A8,CoA!$A$6:$A$46,0)) -> Asset | D8: =INDEX(CoA!$D$6:$D$46,MATCH($A8,CoA!$A$6:$A$46,0)) -> BS | E8: 2980000 | F8: 3150000 | G8: =F8-E8 -> 170000
A9: 1150 | B9: =INDEX(CoA!$B$6:$B$46,MATCH($A9,CoA!$A$6:$A$46,0)) -> Other receivables | C9: =INDEX(CoA!$C$6:$C$46,MATCH($A9,CoA!$A$6:$A$46,0)) -> Asset | D9: =INDEX(CoA!$D$6:$D$46,MATCH($A9,CoA!$A$6:$A$46,0)) -> BS | E9: 590000 | F9: 640000 | G9: =F9-E9 -> 50000
A10: 1200 | B10: =INDEX(CoA!$B$6:$B$46,MATCH($A10,CoA!$A$6:$A$46,0)) -> Inventory - finished goods | C10: =INDEX(CoA!$C$6:$C$46,MATCH($A10,CoA!$A$6:$A$46,0)) -> Asset | D10: =INDEX(CoA!$D$6:$D$46,MATCH($A10,CoA!$A$6:$A$46,0)) -> BS | E10: 93200000 | F10: 96500000 | G10: =F10-E10 -> 3300000
A11: 1210 | B11: =INDEX(CoA!$B$6:$B$46,MATCH($A11,CoA!$A$6:$A$46,0)) -> Inventory in transit | C11: =INDEX(CoA!$C$6:$C$46,MATCH($A11,CoA!$A$6:$A$46,0)) -> Asset | D11: =INDEX(CoA!$D$6:$D$46,MATCH($A11,CoA!$A$6:$A$46,0)) -> BS | E11: 9100000 | F11: 8200000 | G11: =F11-E11 -> -900000
A12: 1300 | B12: =INDEX(CoA!$B$6:$B$46,MATCH($A12,CoA!$A$6:$A$46,0)) -> Prepayments | C12: =INDEX(CoA!$C$6:$C$46,MATCH($A12,CoA!$A$6:$A$46,0)) -> Asset | D12: =INDEX(CoA!$D$6:$D$46,MATCH($A12,CoA!$A$6:$A$46,0)) -> BS | E12: 5150000 | F12: 5400000 | G12: =F12-E12 -> 250000
A13: 1500 | B13: =INDEX(CoA!$B$6:$B$46,MATCH($A13,CoA!$A$6:$A$46,0)) -> Store fit-out - cost | C13: =INDEX(CoA!$C$6:$C$46,MATCH($A13,CoA!$A$6:$A$46,0)) -> Asset | D13: =INDEX(CoA!$D$6:$D$46,MATCH($A13,CoA!$A$6:$A$46,0)) -> BS | E13: 146300000 | F13: 148000000 | G13: =F13-E13 -> 1700000
A14: 1505 | B14: =INDEX(CoA!$B$6:$B$46,MATCH($A14,CoA!$A$6:$A$46,0)) -> IT equipment - cost | C14: =INDEX(CoA!$C$6:$C$46,MATCH($A14,CoA!$A$6:$A$46,0)) -> Asset | D14: =INDEX(CoA!$D$6:$D$46,MATCH($A14,CoA!$A$6:$A$46,0)) -> BS | E14: 21100000 | F14: 21500000 | G14: =F14-E14 -> 400000
A15: 1510 | B15: =INDEX(CoA!$B$6:$B$46,MATCH($A15,CoA!$A$6:$A$46,0)) -> Store fit-out - accumulated depreciation | C15: =INDEX(CoA!$C$6:$C$46,MATCH($A15,CoA!$A$6:$A$46,0)) -> Asset | D15: =INDEX(CoA!$D$6:$D$46,MATCH($A15,CoA!$A$6:$A$46,0)) -> BS | E15: -70000000 | F15: -71200000 | G15: =F15-E15 -> -1200000
A16: 1515 | B16: =INDEX(CoA!$B$6:$B$46,MATCH($A16,CoA!$A$6:$A$46,0)) -> IT equipment - accumulated depreciation | C16: =INDEX(CoA!$C$6:$C$46,MATCH($A16,CoA!$A$6:$A$46,0)) -> Asset | D16: =INDEX(CoA!$D$6:$D$46,MATCH($A16,CoA!$A$6:$A$46,0)) -> BS | E16: -12950000 | F16: -13400000 | G16: =F16-E16 -> -450000
A17: 2000 | B17: =INDEX(CoA!$B$6:$B$46,MATCH($A17,CoA!$A$6:$A$46,0)) -> Trade creditors | C17: =INDEX(CoA!$C$6:$C$46,MATCH($A17,CoA!$A$6:$A$46,0)) -> Liability | D17: =INDEX(CoA!$D$6:$D$46,MATCH($A17,CoA!$A$6:$A$46,0)) -> BS | E17: -26400000 | F17: -27800000 | G17: =F17-E17 -> -1400000
... A29: 3100 | B29: =INDEX(CoA!$B$6:$B$46,MATCH($A29,CoA!$A$6:$A$46,0)) -> Retained earnings - opening | C29: =INDEX(CoA!$C$6:$C$46,MATCH($A29,CoA!$A$6:$A$46,0)) -> Equity | D29: =INDEX(CoA!$D$6:$D$46,MATCH($A29,CoA!$A$6:$A$46,0)) -> BS | E29: -20098000 | F29: -20098000 | G29: =F29-E29 -> 0
A30: 4000 | B30: =INDEX(CoA!$B$6:$B$46,MATCH($A30,CoA!$A$6:$A$46,0)) -> Sales - stores | C30: =INDEX(CoA!$C$6:$C$46,MATCH($A30,CoA!$A$6:$A$46,0)) -> Revenue | D30: =INDEX(CoA!$D$6:$D$46,MATCH($A30,CoA!$A$6:$A$46,0)) -> PL | E30: -74108000 | F30: -112308000 | G30: =F30-E30 -> -38200000 | H30: -37600000 | I30: -35100000
A31: 4010 | B31: =INDEX(CoA!$B$6:$B$46,MATCH($A31,CoA!$A$6:$A$46,0)) -> Sales - online | C31: =INDEX(CoA!$C$6:$C$46,MATCH($A31,CoA!$A$6:$A$46,0)) -> Revenue | D31: =INDEX(CoA!$D$6:$D$46,MATCH($A31,CoA!$A$6:$A$46,0)) -> PL | E31: -26966000 | F31: -40866000 | G31: =F31-E31 -> -13900000 | H31: -14500000 | I31: -11200000
A32: 4900 | B32: =INDEX(CoA!$B$6:$B$46,MATCH($A32,CoA!$A$6:$A$46,0)) -> Sales returns and discounts | C32: =INDEX(CoA!$C$6:$C$46,MATCH($A32,CoA!$A$6:$A$46,0)) -> Revenue | D32: =INDEX(CoA!$D$6:$D$46,MATCH($A32,CoA!$A$6:$A$46,0)) -> PL | E32: 3783000 | F32: 5733000 | G32: =F32-E32 -> 1950000 | H32: 1800000 | I32: 1700000
A33: 5000 | B33: =INDEX(CoA!$B$6:$B$46,MATCH($A33,CoA!$A$6:$A$46,0)) -> Cost of goods sold | C33: =INDEX(CoA!$C$6:$C$46,MATCH($A33,CoA!$A$6:$A$46,0)) -> COGS | D33: =INDEX(CoA!$D$6:$D$46,MATCH($A33,CoA!$A$6:$A$46,0)) -> PL | E33: 38024000 | F33: 57624000 | G33: =F33-E33 -> 19600000 | H33: 19300000 | I33: 18200000
A34: 5010 | B34: =INDEX(CoA!$B$6:$B$46,MATCH($A34,CoA!$A$6:$A$46,0)) -> Freight inwards | C34: =INDEX(CoA!$C$6:$C$46,MATCH($A34,CoA!$A$6:$A$46,0)) -> COGS | D34: =INDEX(CoA!$D$6:$D$46,MATCH($A34,CoA!$A$6:$A$46,0)) -> PL | E34: 3298000 | F34: 4998000 | G34: =F34-E34 -> 1700000 | H34: 1600000 | I34: 1450000
A35: 5020 | B35: =INDEX(CoA!$B$6:$B$46,MATCH($A35,CoA!$A$6:$A$46,0)) -> Inventory shrinkage and provisions | C35: =INDEX(CoA!$C$6:$C$46,MATCH($A35,CoA!$A$6:$A$46,0)) -> COGS | D35: =INDEX(CoA!$D$6:$D$46,MATCH($A35,CoA!$A$6:$A$46,0)) -> PL | E35: 815000 | F35: 1235000 | G35: =F35-E35 -> 420000 | H35: 350000 | I35: 330000
A36: 6000 | B36: =INDEX(CoA!$B$6:$B$46,MATCH($A36,CoA!$A$6:$A$46,0)) -> Wages and salaries - stores | C36: =INDEX(CoA!$C$6:$C$46,MATCH($A36,CoA!$A$6:$A$46,0)) -> Expense | D36: =INDEX(CoA!$D$6:$D$46,MATCH($A36,CoA!$A$6:$A$46,0)) -> PL | E36: 17266000 | F36: 26166000 | G36: =F36-E36 -> 8900000 | H36: 8700000 | I36: 8100000
A37: 6010 | B37: =INDEX(CoA!$B$6:$B$46,MATCH($A37,CoA!$A$6:$A$46,0)) -> Wages and salaries - head office | C37: =INDEX(CoA!$C$6:$C$46,MATCH($A37,CoA!$A$6:$A$46,0)) -> Expense | D37: =INDEX(CoA!$D$6:$D$46,MATCH($A37,CoA!$A$6:$A$46,0)) -> PL | E37: 6014000 | F37: 9114000 | G37: =F37-E37 -> 3100000 | H37: 3050000 | I37: 2800000
A38: 6020 | B38: =INDEX(CoA!$B$6:$B$46,MATCH($A38,CoA!$A$6:$A$46,0)) -> Superannuation expense | C38: =INDEX(CoA!$C$6:$C$46,MATCH($A38,CoA!$A$6:$A$46,0)) -> Expense | D38: =INDEX(CoA!$D$6:$D$46,MATCH($A38,CoA!$A$6:$A$46,0)) -> PL | E38: 2794000 | F38: 4234000 | G38: =F38-E38 -> 1440000 | H38: 1410000 | I38: 1260000
A39: 6100 | B39: =INDEX(CoA!$B$6:$B$46,MATCH($A39,CoA!$A$6:$A$46,0)) -> Rent and occupancy | C39: =INDEX(CoA!$C$6:$C$46,MATCH($A39,CoA!$A$6:$A$46,0)) -> Expense | D39: =INDEX(CoA!$D$6:$D$46,MATCH($A39,CoA!$A$6:$A$46,0)) -> PL | E39: 8342000 | F39: 12642000 | G39: =F39-E39 -> 4300000 | H39: 4300000 | I39: 4050000
A40: 6110 | B40: =INDEX(CoA!$B$6:$B$46,MATCH($A40,CoA!$A$6:$A$46,0)) -> Marketing | C40: =INDEX(CoA!$C$6:$C$46,MATCH($A40,CoA!$A$6:$A$46,0)) -> Expense | D40: =INDEX(CoA!$D$6:$D$46,MATCH($A40,CoA!$A$6:$A$46,0)) -> PL | E40: 6499000 | F40: 9849000 | G40: =F40-E40 -> 3350000 | H40: 3000000 | I40: 2700000
A41: 6120 | B41: =INDEX(CoA!$B$6:$B$46,MATCH($A41,CoA!$A$6:$A$46,0)) -> Depreciation | C41: =INDEX(CoA!$C$6:$C$46,MATCH($A41,CoA!$A$6:$A$46,0)) -> Expense | D41: =INDEX(CoA!$D$6:$D$46,MATCH($A41,CoA!$A$6:$A$46,0)) -> PL | E41: 3201000 | F41: 4851000 | G41: =F41-E41 -> 1650000 | H41: 1600000 | I41: 1500000
... A46: 7000 | B46: =INDEX(CoA!$B$6:$B$46,MATCH($A46,CoA!$A$6:$A$46,0)) -> Interest expense | C46: =INDEX(CoA!$C$6:$C$46,MATCH($A46,CoA!$A$6:$A$46,0)) -> Expense | D46: =INDEX(CoA!$D$6:$D$46,MATCH($A46,CoA!$A$6:$A$46,0)) -> PL | E46: 1242000 | F46: 1882000 | G46: =F46-E46 -> 640000 | H46: 650000 | I46: 700000
B47: Total (must be nil) | E47: =SUM(E6:E46) -> 0 | F47: =SUM(F6:F46) -> 0 | G47: =SUM(G6:G46) -> 0
A49: Notes
A50: 1. All balances are simulated. Cash at bank (1000) closing is set so the TB balances; it is then reconciled to a simulated bank statement on Rec_Bank.
A51: 2. Retained earnings (3100) is the opening balance and is unchanged during the year; P&L accounts hold year-to-date balances.
A52: 3. Budget and prior-year columns are simulated P&L month figures (debit positive).

Sheet Close_Calendar
A1: Month-End Close Calendar
A2: Working-day due dates calculated from the period end (weekends excluded; public holidays not modelled)
A3: Completion: | B3: =COUNTIF(G6:G29,"Complete")/COUNTA(G6:G29) -> 0.375
A5: # | B5: Work day | C5: Due date | D5: Task | E5: Owner | F5: Linked tab | G5: Status | H5: Notes / evidence
A6: 1 | B6: 1 | C6: =WORKDAY(Inputs!$C$5,B6) -> 46296 | D6: Confirm AP, AR, payroll and inventory subledger cut-off | E6: AP / AR / Payroll | F6: - | G6: Complete | H6: Cut-off sign-off emailed
A7: 2 | B7: 1 | C7: =WORKDAY(Inputs!$C$5,B7) -> 46296 | D7: Post daily store sales, card settlement and gift card journals | E7: Treasury | F7: Rec_Bank | G7: Complete
A8: 3 | B8: 1 | C8: =WORKDAY(Inputs!$C$5,B8) -> 46296 | D8: Run and post depreciation for all asset classes | E8: Financial Accountant | F8: FA_Register | G8: Complete | H8: Ties to fixed asset roll-forward
A9: 4 | B9: 2 | C9: =WORKDAY(Inputs!$C$5,B9) -> 46297 | D9: Post payroll journals (wages, PAYG, super) and leave provision movement | E9: Payroll | F9: Rec_Payroll | G9: Complete
A10: 5 | B10: 2 | C10: =WORKDAY(Inputs!$C$5,B10) -> 46297 | D10: Post accruals, GRNI and recurring journals | E10: Financial Accountant | F10: Rec_Accruals | G10: Complete
A11: 6 | B11: 2 | C11: =WORKDAY(Inputs!$C$5,B11) -> 46297 | D11: Post prepayment amortisation | E11: Financial Accountant | F11: Rec_Prepayments | G11: Complete
A12: 7 | B12: 2 | C12: =WORKDAY(Inputs!$C$5,B12) -> 46297 | D12: Bank reconciliation prepared | E12: Treasury | F12: Rec_Bank | G12: Complete
A13: 8 | B13: 3 | C13: =WORKDAY(Inputs!$C$5,B13) -> 46300 | D13: AP subledger to GL reconciliation | E13: AP | F13: Rec_AP | G13: Complete
A14: 9 | B14: 3 | C14: =WORKDAY(Inputs!$C$5,B14) -> 46300 | D14: AR subledger to GL reconciliation | E14: AR | F14: Rec_AR | G14: Complete
A15: 10 | B15: 3 | C15: =WORKDAY(Inputs!$C$5,B15) -> 46300 | D15: Inventory valuation to GL reconciliation; cycle count adjustments | E15: Supply Chain Finance | F15: Rec_Inventory | G15: In progress | H15: Cycle count adjustment pending
A16: 11 | B16: 3 | C16: =WORKDAY(Inputs!$C$5,B16) -> 46300 | D16: Intercompany / other receivables review | E16: AR | F16: - | G16: In progress
A17: 12 | B17: 4 | C17: =WORKDAY(Inputs!$C$5,B17) -> 46301 | D17: GST clearing reconciliation and BAS data extract | E17: Financial Accountant | F17: Rec_GST | G17: In progress
A18: 13 | B18: 4 | C18: =WORKDAY(Inputs!$C$5,B18) -> 46301 | D18: Payroll liabilities reconciliation | E18: Payroll | F18: Rec_Payroll | G18: In progress
A19: 14 | B19: 4 | C19: =WORKDAY(Inputs!$C$5,B19) -> 46301 | D19: Accruals and prepayments reconciliations | E19: Financial Accountant | F19: Rec_Accruals | G19: In progress
A20: 15 | B20: 4 | C20: =WORKDAY(Inputs!$C$5,B20) -> 46301 | D20: Post journals identified in reconciliations | E20: Financial Accountant | F20: Rec_Summary | G20: Not started
A21: 16 | B21: 5 | C21: =WORKDAY(Inputs!$C$5,B21) -> 46302 | D21: Re-run TB; confirm all control checks pass | E21: Financial Accountant | F21: Control | G21: Not started
A22: 17 | B22: 5 | C22: =WORKDAY(Inputs!$C$5,B22) -> 46302 | D22: P&L flux analysis vs budget and prior year; draft commentary | E22: Financial Accountant | F22: Variance | G22: Not started
A23: 18 | B23: 5 | C23: =WORKDAY(Inputs!$C$5,B23) -> 46302 | D23: Fixed asset register roll-forward agrees to GL | E23: Financial Accountant | F23: FA_Register | G23: Not started
A24: 19 | B24: 6 | C24: =WORKDAY(Inputs!$C$5,B24) -> 46303 | D24: Reconciliation review by Financial Controller | E24: Financial Controller | F24: Rec_Summary | G24: Not started
A25: 20 | B25: 6 | C25: =WORKDAY(Inputs!$C$5,B25) -> 46303 | D25: Review of variance commentary with operations and supply chain | E25: Financial Controller | F25: Variance | G25: Not started
A26: 21 | B26: 7 | C26: =WORKDAY(Inputs!$C$5,B26) -> 46304 | D26: Lock period in ERP and issue management accounts pack | E26: Financial Controller | F26: - | G26: Not started
A27: 22 | B27: 7 | C27: =WORKDAY(Inputs!$C$5,B27) -> 46304 | D27: Prepare BAS / IAS for lodgement | E27: Financial Accountant | F27: BAS_IAS | G27: Not started
... A29: 24 | B29: 8 | C29: =WORKDAY(Inputs!$C$5,B29) -> 46307 | D29: Close retrospective: log issues and automation opportunities | E29: Financial Accountant | F29: Automation | G29: Not started

Sheet Rec_Summary
A1: Balance Sheet Reconciliation Summary
A2: Links to each reconciliation tab
A3: Period end: | B3: =Inputs!$C$5 -> 46295
A5: Tab | B5: Account | C5: Balance per GL ($) | D5: Adjusted GL ($) | E5: Adjusted source ($) | F5: Difference ($) | G5: Status | H5: Journals required ($) | I5: Aged items
A6: Rec_Bank | B6: Cash at bank | C6: =Rec_Bank!D10 -> 7190000 | D6: =Rec_Bank!D12 -> 7151590 | E6: =Rec_Bank!D16 -> 7151590 | F6: =Rec_Bank!D18 -> 0 | G6: =Rec_Bank!E18 -> RECONCILED | H6: =Rec_Bank!D11 -> -38410 | I6: =Rec_Bank!D19 -> 1
A7: Rec_AR | B7: Trade debtors | C7: =Rec_AR!D10 -> 3150000 | D7: =Rec_AR!D12 -> 3137400 | E7: =Rec_AR!D16 -> 3137400 | F7: =Rec_AR!D18 -> 0 | G7: =Rec_AR!E18 -> RECONCILED | H7: =Rec_AR!D11 -> -12600 | I7: =Rec_AR!D19 -> 0
A8: Rec_AP | B8: Trade creditors | C8: =Rec_AP!D10 -> 27800000 | D8: =Rec_AP!D12 -> 27831280 | E8: =Rec_AP!D16 -> 27831280 | F8: =Rec_AP!D18 -> 0 | G8: =Rec_AP!E18 -> RECONCILED | H8: =Rec_AP!D11 -> 31280 | I8: =Rec_AP!D19 -> 0
A9: Rec_Inventory | B9: Inventory (finished goods and in transit) | C9: =Rec_Inventory!D10 -> 104700000 | D9: =Rec_Inventory!D12 -> 104435000 | E9: =Rec_Inventory!D16 -> 104435000 | F9: =Rec_Inventory!D18 -> 0 | G9: =Rec_Inventory!E18 -> RECONCILED | H9: =Rec_Inventory!D11 -> -265000 | I9: =Rec_Inventory!D19 -> 0
A10: Rec_Accruals | B10: Accrued expenses and GRNI | C10: =Rec_Accruals!D10 -> 11200000 | D10: =Rec_Accruals!D12 -> 10982000 | E10: =Rec_Accruals!D16 -> 10982000 | F10: =Rec_Accruals!D18 -> 0 | G10: =Rec_Accruals!E18 -> RECONCILED | H10: =Rec_Accruals!D11 -> -218000 | I10: =Rec_Accruals!D19 -> 0
A11: Rec_Prepayments | B11: Prepayments | C11: =Rec_Prepayments!D10 -> 5400000 | D11: =Rec_Prepayments!D12 -> 5358250 | E11: =Rec_Prepayments!D16 -> 5358250 | F11: =Rec_Prepayments!D18 -> 0 | G11: =Rec_Prepayments!E18 -> RECONCILED | H11: =Rec_Prepayments!D11 -> -41750 | I11: =Rec_Prepayments!D19 -> 0
A12: Rec_GST | B12: GST clearing (net GST payable) | C12: =Rec_GST!D10 -> 2665000 | D12: =Rec_GST!D12 -> 2656580 | E12: =Rec_GST!D16 -> 2656580 | F12: =Rec_GST!D18 -> 0 | G12: =Rec_GST!E18 -> RECONCILED | H12: =Rec_GST!D11 -> -8420 | I12: =Rec_GST!D19 -> 0
A13: Rec_Payroll | B13: Payroll liabilities (PAYG, super, accrued wages) | C13: =Rec_Payroll!D10 -> 4595000 | D13: =Rec_Payroll!D12 -> 4499000 | E13: =Rec_Payroll!D16 -> 4499000 | F13: =Rec_Payroll!D18 -> 0 | G13: =Rec_Payroll!E18 -> RECONCILED | H13: =Rec_Payroll!D11 -> -96000 | I13: =Rec_Payroll!D19 -> 0
B14: Total | F14: =SUM(F6:F13) -> 0 | H14: =SUM(H6:H13) -> -648900 | I14: =SUM(I6:I13) -> 1
A16: Journals required are the GL adjustments identified in reconciliation; post them before the P&L is finalised and re-run the TB.

Sheet Rec_Bank
A1: Balance Sheet Reconciliation - Cash at bank
A2: =Inputs!$C$3 -> Specialty retailer (simulated, Adairs-style)
A4: Period end | B4: =Inputs!$C$5 -> 46295
A5: GL account 1 | B5: 1000 | C5: =INDEX(CoA!$B$6:$B$46,MATCH($B5,CoA!$A$6:$A$46,0)) -> Cash at bank - operating
A6: GL account 2
A7: GL account 3
A8: Sign factor (1 = debit balance; -1 = credit balance shown positive) | B8: 1
A10: Balance per GL (TB closing) | D10: =$B$8*(IF($B$5="",0,SUMIF(TB!$A$6:$A$46,$B$5,TB!$F$6:$F$46))+IF($B$6="",0,SUMIF(TB!$A$6:$A$46,$B$6,TB!$F$6:$F$46))+IF($B$7="",0,SUMIF(TB!$A$6:$A$46,$B$7,TB!$F$6:$F$46))) -> 7190000
A11: Add / (less): GL adjustments (journals required) | D11: =SUMIF($E$22:$E$41,"GL adjustment",$D$22:$D$41) -> -38410
A12: Adjusted GL balance | D12: =D10+D11 -> 7151590
A14: Balance per source: | B14: Bank statement balance 30-Sep-2026 | D14: 6638170
A15: Add / (less): timing items (clear next period) | D15: =SUMIF($E$22:$E$41,"Timing",$D$22:$D$41) -> 513420
A16: Adjusted source balance | D16: =D14+D15 -> 7151590
A18: Unreconciled difference (adjusted GL less adjusted source) | D18: =ROUND(D12-D16,2) -> 0 | E18: =IF(ABS(D18)<=Inputs!$C$12,"RECONCILED","INVESTIGATE") -> RECONCILED
A19: Items older than ageing threshold | D19: =COUNTIF($G$22:$G$41,"Aged") -> 1
A21: Ref | B21: Description of reconciling item | C21: Item date | D21: Amount ($) | E21: Type | F21: Days open | G21: Aged? | H21: Action / owner | I21: Expected clear
A22: BNK-01 | B22: Merchant fees per bank statement not yet journalised | C22: 46295 | D22: -38410 | E22: GL adjustment | F22: =IF($C22="","",$B$4-$C22) -> 0 | G22: =IF($F22="","",IF($F22>Inputs!$C$9,"Aged","")) | H22: Journal: Dr 6150 / Cr 1000 - Treasury | I22: 46297
A23: BNK-02 | B23: Card settlement trading 30-Sep banked 1-Oct (deposit in transit) | C23: 46295 | D23: 1420350 | E23: Timing | F23: =IF($C23="","",$B$4-$C23) -> 0 | G23: =IF($F23="","",IF($F23>Inputs!$C$9,"Aged","")) | H23: Clears 1-Oct - Treasury | I23: 46296
A24: BNK-03 | B24: Supplier EFT batch released 29-Sep, cleared 1-Oct (outstanding payment) | C24: 46294 | D24: -845200 | E24: Timing | F24: =IF($C24="","",$B$4-$C24) -> 1 | G24: =IF($F24="","",IF($F24>Inputs!$C$9,"Aged","")) | H24: Clears 1-Oct - AP | I24: 46296
A25: BNK-04 | B25: Unpresented refund payments | C25: 46261 | D25: -61730 | E25: Timing | F25: =IF($C25="","",$B$4-$C25) -> 34 | G25: =IF($F25="","",IF($F25>Inputs!$C$9,"Aged","")) -> Aged | H25: Chase / reverse if stale - Treasury | I25: 46304
F26: =IF($C26="","",$B$4-$C26) | G26: =IF($F26="","",IF($F26>Inputs!$C$9,"Aged",""))
F27: =IF($C27="","",$B$4-$C27) | G27: =IF($F27="","",IF($F27>Inputs!$C$9,"Aged",""))
F28: =IF($C28="","",$B$4-$C28) | G28: =IF($F28="","",IF($F28>Inputs!$C$9,"Aged",""))
F29: =IF($C29="","",$B$4-$C29) | G29: =IF($F29="","",IF($F29>Inputs!$C$9,"Aged",""))
F30: =IF($C30="","",$B$4-$C30) | G30: =IF($F30="","",IF($F30>Inputs!$C$9,"Aged",""))
F31: =IF($C31="","",$B$4-$C31) | G31: =IF($F31="","",IF($F31>Inputs!$C$9,"Aged",""))
F32: =IF($C32="","",$B$4-$C32) | G32: =IF($F32="","",IF($F32>Inputs!$C$9,"Aged",""))
F33: =IF($C33="","",$B$4-$C33) | G33: =IF($F33="","",IF($F33>Inputs!$C$9,"Aged",""))
F34: =IF($C34="","",$B$4-$C34) | G34: =IF($F34="","",IF($F34>Inputs!$C$9,"Aged",""))
F35: =IF($C35="","",$B$4-$C35) | G35: =IF($F35="","",IF($F35>Inputs!$C$9,"Aged",""))
F36: =IF($C36="","",$B$4-$C36) | G36: =IF($F36="","",IF($F36>Inputs!$C$9,"Aged",""))
F37: =IF($C37="","",$B$4-$C37) | G37: =IF($F37="","",IF($F37>Inputs!$C$9,"Aged",""))
... F41: =IF($C41="","",$B$4-$C41) | G41: =IF($F41="","",IF($F41>Inputs!$C$9,"Aged",""))
A44: Sign-off
A45: Prepared by | B45: =Inputs!$C$6 -> Bhagyashree Amblimath | C45: 46300
A46: Reviewed by | B46: =Inputs!$C$7 -> Financial Controller (simulated) | D46: <- reviewer to date on sign-off
A48: Template notes: 'Timing' items clear on their own next period; 'GL adjustment' items need a journal. Source balance and items are simulated and hardcoded (blue); the difference must be nil.

Sheet Rec_AR
A1: Balance Sheet Reconciliation - Trade debtors
A2: =Inputs!$C$3 -> Specialty retailer (simulated, Adairs-style)
A4: Period end | B4: =Inputs!$C$5 -> 46295
A5: GL account 1 | B5: 1100 | C5: =INDEX(CoA!$B$6:$B$46,MATCH($B5,CoA!$A$6:$A$46,0)) -> Trade debtors
A6: GL account 2
A7: GL account 3
A8: Sign factor (1 = debit balance; -1 = credit balance shown positive) | B8: 1
A10: Balance per GL (TB closing) | D10: =$B$8*(IF($B$5="",0,SUMIF(TB!$A$6:$A$46,$B$5,TB!$F$6:$F$46))+IF($B$6="",0,SUMIF(TB!$A$6:$A$46,$B$6,TB!$F$6:$F$46))+IF($B$7="",0,SUMIF(TB!$A$6:$A$46,$B$7,TB!$F$6:$F$46))) -> 3150000
A11: Add / (less): GL adjustments (journals required) | D11: =SUMIF($E$22:$E$41,"GL adjustment",$D$22:$D$41) -> -12600
A12: Adjusted GL balance | D12: =D10+D11 -> 3137400
A14: Balance per source: | B14: AR subledger aged trial balance | D14: 3323800
A15: Add / (less): timing items (clear next period) | D15: =SUMIF($E$22:$E$41,"Timing",$D$22:$D$41) -> -186400
A16: Adjusted source balance | D16: =D14+D15 -> 3137400
A18: Unreconciled difference (adjusted GL less adjusted source) | D18: =ROUND(D12-D16,2) -> 0 | E18: =IF(ABS(D18)<=Inputs!$C$12,"RECONCILED","INVESTIGATE") -> RECONCILED
A19: Items older than ageing threshold | D19: =COUNTIF($G$22:$G$41,"Aged") -> 0
A21: Ref | B21: Description of reconciling item | C21: Item date | D21: Amount ($) | E21: Type | F21: Days open | G21: Aged? | H21: Action / owner | I21: Expected clear
A22: AR-01 | B22: Credit note CN-4471 in subledger; interface to GL failed | C22: 46293 | D22: -12600 | E22: GL adjustment | F22: =IF($C22="","",$B$4-$C22) -> 2 | G22: =IF($F22="","",IF($F22>Inputs!$C$9,"Aged","")) | H22: Journal: Dr 4900 / Cr 1100 - AR | I22: 46297
A23: AR-02 | B23: Customer remittance banked 30-Sep, applied in subledger 1-Oct | C23: 46295 | D23: -186400 | E23: Timing | F23: =IF($C23="","",$B$4-$C23) -> 0 | G23: =IF($F23="","",IF($F23>Inputs!$C$9,"Aged","")) | H23: Clears 1-Oct - AR | I23: 46296
F24: =IF($C24="","",$B$4-$C24) | G24: =IF($F24="","",IF($F24>Inputs!$C$9,"Aged",""))
F25: =IF($C25="","",$B$4-$C25) | G25: =IF($F25="","",IF($F25>Inputs!$C$9,"Aged",""))
F26: =IF($C26="","",$B$4-$C26) | G26: =IF($F26="","",IF($F26>Inputs!$C$9,"Aged",""))
F27: =IF($C27="","",$B$4-$C27) | G27: =IF($F27="","",IF($F27>Inputs!$C$9,"Aged",""))
F28: =IF($C28="","",$B$4-$C28) | G28: =IF($F28="","",IF($F28>Inputs!$C$9,"Aged",""))
F29: =IF($C29="","",$B$4-$C29) | G29: =IF($F29="","",IF($F29>Inputs!$C$9,"Aged",""))
F30: =IF($C30="","",$B$4-$C30) | G30: =IF($F30="","",IF($F30>Inputs!$C$9,"Aged",""))
F31: =IF($C31="","",$B$4-$C31) | G31: =IF($F31="","",IF($F31>Inputs!$C$9,"Aged",""))
F32: =IF($C32="","",$B$4-$C32) | G32: =IF($F32="","",IF($F32>Inputs!$C$9,"Aged",""))
F33: =IF($C33="","",$B$4-$C33) | G33: =IF($F33="","",IF($F33>Inputs!$C$9,"Aged",""))
F34: =IF($C34="","",$B$4-$C34) | G34: =IF($F34="","",IF($F34>Inputs!$C$9,"Aged",""))
F35: =IF($C35="","",$B$4-$C35) | G35: =IF($F35="","",IF($F35>Inputs!$C$9,"Aged",""))
... F41: =IF($C41="","",$B$4-$C41) | G41: =IF($F41="","",IF($F41>Inputs!$C$9,"Aged",""))
A44: Sign-off
A45: Prepared by | B45: =Inputs!$C$6 -> Bhagyashree Amblimath | C45: 46300
A46: Reviewed by | B46: =Inputs!$C$7 -> Financial Controller (simulated) | D46: <- reviewer to date on sign-off
A48: Template notes: 'Timing' items clear on their own next period; 'GL adjustment' items need a journal. Source balance and items are simulated and hardcoded (blue); the difference must be nil.

Sheet Rec_AP
A1: Balance Sheet Reconciliation - Trade creditors
A2: =Inputs!$C$3 -> Specialty retailer (simulated, Adairs-style)
A4: Period end | B4: =Inputs!$C$5 -> 46295
A5: GL account 1 | B5: 2000 | C5: =INDEX(CoA!$B$6:$B$46,MATCH($B5,CoA!$A$6:$A$46,0)) -> Trade creditors
A6: GL account 2
A7: GL account 3
A8: Sign factor (1 = debit balance; -1 = credit balance shown positive) | B8: -1
A10: Balance per GL (TB closing) | D10: =$B$8*(IF($B$5="",0,SUMIF(TB!$A$6:$A$46,$B$5,TB!$F$6:$F$46))+IF($B$6="",0,SUMIF(TB!$A$6:$A$46,$B$6,TB!$F$6:$F$46))+IF($B$7="",0,SUMIF(TB!$A$6:$A$46,$B$7,TB!$F$6:$F$46))) -> 27800000
A11: Add / (less): GL adjustments (journals required) | D11: =SUMIF($E$22:$E$41,"GL adjustment",$D$22:$D$41) -> 31280
A12: Adjusted GL balance | D12: =D10+D11 -> 27831280
A14: Balance per source: | B14: AP subledger creditor listing | D14: 27886180
A15: Add / (less): timing items (clear next period) | D15: =SUMIF($E$22:$E$41,"Timing",$D$22:$D$41) -> -54900
A16: Adjusted source balance | D16: =D14+D15 -> 27831280
A18: Unreconciled difference (adjusted GL less adjusted source) | D18: =ROUND(D12-D16,2) -> 0 | E18: =IF(ABS(D18)<=Inputs!$C$12,"RECONCILED","INVESTIGATE") -> RECONCILED
A19: Items older than ageing threshold | D19: =COUNTIF($G$22:$G$41,"Aged") -> 0
A21: Ref | B21: Description of reconciling item | C21: Item date | D21: Amount ($) | E21: Type | F21: Days open | G21: Aged? | H21: Action / owner | I21: Expected clear
A22: AP-01 | B22: Invoice INV-88231 in AP subledger; GL interface error | C22: 46294 | D22: 31280 | E22: GL adjustment | F22: =IF($C22="","",$B$4-$C22) -> 1 | G22: =IF($F22="","",IF($F22>Inputs!$C$9,"Aged","")) | H22: Re-run interface / manual journal - AP | I22: 46297
A23: AP-02 | B23: Supplier debit note recorded in GL 30-Sep, subledger 1-Oct | C23: 46295 | D23: -54900 | E23: Timing | F23: =IF($C23="","",$B$4-$C23) -> 0 | G23: =IF($F23="","",IF($F23>Inputs!$C$9,"Aged","")) | H23: Clears 1-Oct - AP | I23: 46296
F24: =IF($C24="","",$B$4-$C24) | G24: =IF($F24="","",IF($F24>Inputs!$C$9,"Aged",""))
F25: =IF($C25="","",$B$4-$C25) | G25: =IF($F25="","",IF($F25>Inputs!$C$9,"Aged",""))
F26: =IF($C26="","",$B$4-$C26) | G26: =IF($F26="","",IF($F26>Inputs!$C$9,"Aged",""))
F27: =IF($C27="","",$B$4-$C27) | G27: =IF($F27="","",IF($F27>Inputs!$C$9,"Aged",""))
F28: =IF($C28="","",$B$4-$C28) | G28: =IF($F28="","",IF($F28>Inputs!$C$9,"Aged",""))
F29: =IF($C29="","",$B$4-$C29) | G29: =IF($F29="","",IF($F29>Inputs!$C$9,"Aged",""))
F30: =IF($C30="","",$B$4-$C30) | G30: =IF($F30="","",IF($F30>Inputs!$C$9,"Aged",""))
F31: =IF($C31="","",$B$4-$C31) | G31: =IF($F31="","",IF($F31>Inputs!$C$9,"Aged",""))
F32: =IF($C32="","",$B$4-$C32) | G32: =IF($F32="","",IF($F32>Inputs!$C$9,"Aged",""))
F33: =IF($C33="","",$B$4-$C33) | G33: =IF($F33="","",IF($F33>Inputs!$C$9,"Aged",""))
F34: =IF($C34="","",$B$4-$C34) | G34: =IF($F34="","",IF($F34>Inputs!$C$9,"Aged",""))
F35: =IF($C35="","",$B$4-$C35) | G35: =IF($F35="","",IF($F35>Inputs!$C$9,"Aged",""))
... F41: =IF($C41="","",$B$4-$C41) | G41: =IF($F41="","",IF($F41>Inputs!$C$9,"Aged",""))
A44: Sign-off
A45: Prepared by | B45: =Inputs!$C$6 -> Bhagyashree Amblimath | C45: 46300
A46: Reviewed by | B46: =Inputs!$C$7 -> Financial Controller (simulated) | D46: <- reviewer to date on sign-off
A48: Template notes: 'Timing' items clear on their own next period; 'GL adjustment' items need a journal. Source balance and items are simulated and hardcoded (blue); the difference must be nil.

Sheet Rec_Inventory
A1: Balance Sheet Reconciliation - Inventory (finished goods and in transit)
A2: =Inputs!$C$3 -> Specialty retailer (simulated, Adairs-style)
A4: Period end | B4: =Inputs!$C$5 -> 46295
A5: GL account 1 | B5: 1200 | C5: =INDEX(CoA!$B$6:$B$46,MATCH($B5,CoA!$A$6:$A$46,0)) -> Inventory - finished goods
A6: GL account 2 | B6: 1210 | C6: =INDEX(CoA!$B$6:$B$46,MATCH($B6,CoA!$A$6:$A$46,0)) -> Inventory in transit
A7: GL account 3
A8: Sign factor (1 = debit balance; -1 = credit balance shown positive) | B8: 1
A10: Balance per GL (TB closing) | D10: =$B$8*(IF($B$5="",0,SUMIF(TB!$A$6:$A$46,$B$5,TB!$F$6:$F$46))+IF($B$6="",0,SUMIF(TB!$A$6:$A$46,$B$6,TB!$F$6:$F$46))+IF($B$7="",0,SUMIF(TB!$A$6:$A$46,$B$7,TB!$F$6:$F$46))) -> 104700000
A11: Add / (less): GL adjustments (journals required) | D11: =SUMIF($E$22:$E$41,"GL adjustment",$D$22:$D$41) -> -265000
A12: Adjusted GL balance | D12: =D10+D11 -> 104435000
A14: Balance per source: | B14: WMS valuation plus shipping report | D14: 104124500
A15: Add / (less): timing items (clear next period) | D15: =SUMIF($E$22:$E$41,"Timing",$D$22:$D$41) -> 310500
A16: Adjusted source balance | D16: =D14+D15 -> 104435000
A18: Unreconciled difference (adjusted GL less adjusted source) | D18: =ROUND(D12-D16,2) -> 0 | E18: =IF(ABS(D18)<=Inputs!$C$12,"RECONCILED","INVESTIGATE") -> RECONCILED
A19: Items older than ageing threshold | D19: =COUNTIF($G$22:$G$41,"Aged") -> 0
A21: Ref | B21: Description of reconciling item | C21: Item date | D21: Amount ($) | E21: Type | F21: Days open | G21: Aged? | H21: Action / owner | I21: Expected clear
A22: INV-01 | B22: Q1 cycle count variance; stock adjustment not yet posted | C22: 46291 | D22: -265000 | E22: GL adjustment | F22: =IF($C22="","",$B$4-$C22) -> 4 | G22: =IF($F22="","",IF($F22>Inputs!$C$9,"Aged","")) | H22: Journal: Dr 5020 / Cr 1200 - Supply Chain Finance | I22: 46298
A23: INV-02 | B23: Receipts in GL 30-Sep, booked in WMS 1-Oct | C23: 46295 | D23: 310500 | E23: Timing | F23: =IF($C23="","",$B$4-$C23) -> 0 | G23: =IF($F23="","",IF($F23>Inputs!$C$9,"Aged","")) | H23: Clears 1-Oct - Supply Chain | I23: 46296
F24: =IF($C24="","",$B$4-$C24) | G24: =IF($F24="","",IF($F24>Inputs!$C$9,"Aged",""))
F25: =IF($C25="","",$B$4-$C25) | G25: =IF($F25="","",IF($F25>Inputs!$C$9,"Aged",""))
F26: =IF($C26="","",$B$4-$C26) | G26: =IF($F26="","",IF($F26>Inputs!$C$9,"Aged",""))
F27: =IF($C27="","",$B$4-$C27) | G27: =IF($F27="","",IF($F27>Inputs!$C$9,"Aged",""))
F28: =IF($C28="","",$B$4-$C28) | G28: =IF($F28="","",IF($F28>Inputs!$C$9,"Aged",""))
F29: =IF($C29="","",$B$4-$C29) | G29: =IF($F29="","",IF($F29>Inputs!$C$9,"Aged",""))
F30: =IF($C30="","",$B$4-$C30) | G30: =IF($F30="","",IF($F30>Inputs!$C$9,"Aged",""))
F31: =IF($C31="","",$B$4-$C31) | G31: =IF($F31="","",IF($F31>Inputs!$C$9,"Aged",""))
F32: =IF($C32="","",$B$4-$C32) | G32: =IF($F32="","",IF($F32>Inputs!$C$9,"Aged",""))
F33: =IF($C33="","",$B$4-$C33) | G33: =IF($F33="","",IF($F33>Inputs!$C$9,"Aged",""))
F34: =IF($C34="","",$B$4-$C34) | G34: =IF($F34="","",IF($F34>Inputs!$C$9,"Aged",""))
F35: =IF($C35="","",$B$4-$C35) | G35: =IF($F35="","",IF($F35>Inputs!$C$9,"Aged",""))
... F41: =IF($C41="","",$B$4-$C41) | G41: =IF($F41="","",IF($F41>Inputs!$C$9,"Aged",""))
A44: Sign-off
A45: Prepared by | B45: =Inputs!$C$6 -> Bhagyashree Amblimath | C45: 46300
A46: Reviewed by | B46: =Inputs!$C$7 -> Financial Controller (simulated) | D46: <- reviewer to date on sign-off
A48: Template notes: 'Timing' items clear on their own next period; 'GL adjustment' items need a journal. Source balance and items are simulated and hardcoded (blue); the difference must be nil.

Sheet Rec_Accruals
A1: Balance Sheet Reconciliation - Accrued expenses and GRNI
A2: =Inputs!$C$3 -> Specialty retailer (simulated, Adairs-style)
A4: Period end | B4: =Inputs!$C$5 -> 46295
A5: GL account 1 | B5: 2010 | C5: =INDEX(CoA!$B$6:$B$46,MATCH($B5,CoA!$A$6:$A$46,0)) -> Accrued expenses
A6: GL account 2 | B6: 2020 | C6: =INDEX(CoA!$B$6:$B$46,MATCH($B6,CoA!$A$6:$A$46,0)) -> Goods received not invoiced (GRNI)
A7: GL account 3
A8: Sign factor (1 = debit balance; -1 = credit balance shown positive) | B8: -1
A10: Balance per GL (TB closing) | D10: =$B$8*(IF($B$5="",0,SUMIF(TB!$A$6:$A$46,$B$5,TB!$F$6:$F$46))+IF($B$6="",0,SUMIF(TB!$A$6:$A$46,$B$6,TB!$F$6:$F$46))+IF($B$7="",0,SUMIF(TB!$A$6:$A$46,$B$7,TB!$F$6:$F$46))) -> 11200000
A11: Add / (less): GL adjustments (journals required) | D11: =SUMIF($E$22:$E$41,"GL adjustment",$D$22:$D$41) -> -218000
A12: Adjusted GL balance | D12: =D10+D11 -> 10982000
A14: Balance per source: | B14: Accruals and GRNI schedule | D14: 10887000
A15: Add / (less): timing items (clear next period) | D15: =SUMIF($E$22:$E$41,"Timing",$D$22:$D$41) -> 95000
A16: Adjusted source balance | D16: =D14+D15 -> 10982000
A18: Unreconciled difference (adjusted GL less adjusted source) | D18: =ROUND(D12-D16,2) -> 0 | E18: =IF(ABS(D18)<=Inputs!$C$12,"RECONCILED","INVESTIGATE") -> RECONCILED
A19: Items older than ageing threshold | D19: =COUNTIF($G$22:$G$41,"Aged") -> 0
A21: Ref | B21: Description of reconciling item | C21: Item date | D21: Amount ($) | E21: Type | F21: Days open | G21: Aged? | H21: Action / owner | I21: Expected clear
A22: ACC-01 | B22: Rent accrual reversal not posted for September | C22: 46295 | D22: -218000 | E22: GL adjustment | F22: =IF($C22="","",$B$4-$C22) -> 0 | G22: =IF($F22="","",IF($F22>Inputs!$C$9,"Aged","")) | H22: Journal: Dr 2010 / Cr 6100 - Financial Accountant | I22: 46297
A23: ACC-02 | B23: Accrual raised 30-Sep after schedule cut-off | C23: 46295 | D23: 95000 | E23: Timing | F23: =IF($C23="","",$B$4-$C23) -> 0 | G23: =IF($F23="","",IF($F23>Inputs!$C$9,"Aged","")) | H23: Added to schedule 1-Oct | I23: 46296
F24: =IF($C24="","",$B$4-$C24) | G24: =IF($F24="","",IF($F24>Inputs!$C$9,"Aged",""))
F25: =IF($C25="","",$B$4-$C25) | G25: =IF($F25="","",IF($F25>Inputs!$C$9,"Aged",""))
F26: =IF($C26="","",$B$4-$C26) | G26: =IF($F26="","",IF($F26>Inputs!$C$9,"Aged",""))
F27: =IF($C27="","",$B$4-$C27) | G27: =IF($F27="","",IF($F27>Inputs!$C$9,"Aged",""))
F28: =IF($C28="","",$B$4-$C28) | G28: =IF($F28="","",IF($F28>Inputs!$C$9,"Aged",""))
F29: =IF($C29="","",$B$4-$C29) | G29: =IF($F29="","",IF($F29>Inputs!$C$9,"Aged",""))
F30: =IF($C30="","",$B$4-$C30) | G30: =IF($F30="","",IF($F30>Inputs!$C$9,"Aged",""))
F31: =IF($C31="","",$B$4-$C31) | G31: =IF($F31="","",IF($F31>Inputs!$C$9,"Aged",""))
F32: =IF($C32="","",$B$4-$C32) | G32: =IF($F32="","",IF($F32>Inputs!$C$9,"Aged",""))
F33: =IF($C33="","",$B$4-$C33) | G33: =IF($F33="","",IF($F33>Inputs!$C$9,"Aged",""))
F34: =IF($C34="","",$B$4-$C34) | G34: =IF($F34="","",IF($F34>Inputs!$C$9,"Aged",""))
F35: =IF($C35="","",$B$4-$C35) | G35: =IF($F35="","",IF($F35>Inputs!$C$9,"Aged",""))
... F41: =IF($C41="","",$B$4-$C41) | G41: =IF($F41="","",IF($F41>Inputs!$C$9,"Aged",""))
A44: Sign-off
A45: Prepared by | B45: =Inputs!$C$6 -> Bhagyashree Amblimath | C45: 46300
A46: Reviewed by | B46: =Inputs!$C$7 -> Financial Controller (simulated) | D46: <- reviewer to date on sign-off
A48: Template notes: 'Timing' items clear on their own next period; 'GL adjustment' items need a journal. Source balance and items are simulated and hardcoded (blue); the difference must be nil.

Sheet Rec_Prepayments
A1: Balance Sheet Reconciliation - Prepayments
A2: =Inputs!$C$3 -> Specialty retailer (simulated, Adairs-style)
A4: Period end | B4: =Inputs!$C$5 -> 46295
A5: GL account 1 | B5: 1300 | C5: =INDEX(CoA!$B$6:$B$46,MATCH($B5,CoA!$A$6:$A$46,0)) -> Prepayments
A6: GL account 2
A7: GL account 3
A8: Sign factor (1 = debit balance; -1 = credit balance shown positive) | B8: 1
A10: Balance per GL (TB closing) | D10: =$B$8*(IF($B$5="",0,SUMIF(TB!$A$6:$A$46,$B$5,TB!$F$6:$F$46))+IF($B$6="",0,SUMIF(TB!$A$6:$A$46,$B$6,TB!$F$6:$F$46))+IF($B$7="",0,SUMIF(TB!$A$6:$A$46,$B$7,TB!$F$6:$F$46))) -> 5400000
A11: Add / (less): GL adjustments (journals required) | D11: =SUMIF($E$22:$E$41,"GL adjustment",$D$22:$D$41) -> -41750
A12: Adjusted GL balance | D12: =D10+D11 -> 5358250
A14: Balance per source: | B14: Prepayment amortisation schedule | D14: 5238250
A15: Add / (less): timing items (clear next period) | D15: =SUMIF($E$22:$E$41,"Timing",$D$22:$D$41) -> 120000
A16: Adjusted source balance | D16: =D14+D15 -> 5358250
A18: Unreconciled difference (adjusted GL less adjusted source) | D18: =ROUND(D12-D16,2) -> 0 | E18: =IF(ABS(D18)<=Inputs!$C$12,"RECONCILED","INVESTIGATE") -> RECONCILED
A19: Items older than ageing threshold | D19: =COUNTIF($G$22:$G$41,"Aged") -> 0
A21: Ref | B21: Description of reconciling item | C21: Item date | D21: Amount ($) | E21: Type | F21: Days open | G21: Aged? | H21: Action / owner | I21: Expected clear
A22: PRE-01 | B22: September insurance amortisation not booked | C22: 46295 | D22: -41750 | E22: GL adjustment | F22: =IF($C22="","",$B$4-$C22) -> 0 | G22: =IF($F22="","",IF($F22>Inputs!$C$9,"Aged","")) | H22: Journal: Dr 6160 / Cr 1300 - Financial Accountant | I22: 46297
A23: PRE-02 | B23: Licence prepayment added to schedule 1-Oct, in GL 30-Sep | C23: 46295 | D23: 120000 | E23: Timing | F23: =IF($C23="","",$B$4-$C23) -> 0 | G23: =IF($F23="","",IF($F23>Inputs!$C$9,"Aged","")) | H23: Clears 1-Oct | I23: 46296
F24: =IF($C24="","",$B$4-$C24) | G24: =IF($F24="","",IF($F24>Inputs!$C$9,"Aged",""))
F25: =IF($C25="","",$B$4-$C25) | G25: =IF($F25="","",IF($F25>Inputs!$C$9,"Aged",""))
F26: =IF($C26="","",$B$4-$C26) | G26: =IF($F26="","",IF($F26>Inputs!$C$9,"Aged",""))
F27: =IF($C27="","",$B$4-$C27) | G27: =IF($F27="","",IF($F27>Inputs!$C$9,"Aged",""))
F28: =IF($C28="","",$B$4-$C28) | G28: =IF($F28="","",IF($F28>Inputs!$C$9,"Aged",""))
F29: =IF($C29="","",$B$4-$C29) | G29: =IF($F29="","",IF($F29>Inputs!$C$9,"Aged",""))
F30: =IF($C30="","",$B$4-$C30) | G30: =IF($F30="","",IF($F30>Inputs!$C$9,"Aged",""))
F31: =IF($C31="","",$B$4-$C31) | G31: =IF($F31="","",IF($F31>Inputs!$C$9,"Aged",""))
F32: =IF($C32="","",$B$4-$C32) | G32: =IF($F32="","",IF($F32>Inputs!$C$9,"Aged",""))
F33: =IF($C33="","",$B$4-$C33) | G33: =IF($F33="","",IF($F33>Inputs!$C$9,"Aged",""))
F34: =IF($C34="","",$B$4-$C34) | G34: =IF($F34="","",IF($F34>Inputs!$C$9,"Aged",""))
F35: =IF($C35="","",$B$4-$C35) | G35: =IF($F35="","",IF($F35>Inputs!$C$9,"Aged",""))
... F41: =IF($C41="","",$B$4-$C41) | G41: =IF($F41="","",IF($F41>Inputs!$C$9,"Aged",""))
A44: Sign-off
A45: Prepared by | B45: =Inputs!$C$6 -> Bhagyashree Amblimath | C45: 46300
A46: Reviewed by | B46: =Inputs!$C$7 -> Financial Controller (simulated) | D46: <- reviewer to date on sign-off
A48: Template notes: 'Timing' items clear on their own next period; 'GL adjustment' items need a journal. Source balance and items are simulated and hardcoded (blue); the difference must be nil.

Sheet Rec_GST
A1: Balance Sheet Reconciliation - GST clearing (net GST payable)
A2: =Inputs!$C$3 -> Specialty retailer (simulated, Adairs-style)
A4: Period end | B4: =Inputs!$C$5 -> 46295
A5: GL account 1 | B5: 2300 | C5: =INDEX(CoA!$B$6:$B$46,MATCH($B5,CoA!$A$6:$A$46,0)) -> GST collected
A6: GL account 2 | B6: 2310 | C6: =INDEX(CoA!$B$6:$B$46,MATCH($B6,CoA!$A$6:$A$46,0)) -> GST paid (input tax credits)
A7: GL account 3
A8: Sign factor (1 = debit balance; -1 = credit balance shown positive) | B8: -1
A10: Balance per GL (TB closing) | D10: =$B$8*(IF($B$5="",0,SUMIF(TB!$A$6:$A$46,$B$5,TB!$F$6:$F$46))+IF($B$6="",0,SUMIF(TB!$A$6:$A$46,$B$6,TB!$F$6:$F$46))+IF($B$7="",0,SUMIF(TB!$A$6:$A$46,$B$7,TB!$F$6:$F$46))) -> 2665000
A11: Add / (less): GL adjustments (journals required) | D11: =SUMIF($E$22:$E$41,"GL adjustment",$D$22:$D$41) -> -8420
A12: Adjusted GL balance | D12: =D10+D11 -> 2656580
A14: Balance per source: | B14: BAS_IAS tab: net GST payable (1A less 1B) | D14: =BAS_IAS!D23 -> 2642280
A15: Add / (less): timing items (clear next period) | D15: =SUMIF($E$22:$E$41,"Timing",$D$22:$D$41) -> 14300
A16: Adjusted source balance | D16: =D14+D15 -> 2656580
A18: Unreconciled difference (adjusted GL less adjusted source) | D18: =ROUND(D12-D16,2) -> 0 | E18: =IF(ABS(D18)<=Inputs!$C$12,"RECONCILED","INVESTIGATE") -> RECONCILED
A19: Items older than ageing threshold | D19: =COUNTIF($G$22:$G$41,"Aged") -> 0
A21: Ref | B21: Description of reconciling item | C21: Item date | D21: Amount ($) | E21: Type | F21: Days open | G21: Aged? | H21: Action / owner | I21: Expected clear
A22: GST-01 | B22: GST on petty cash and card purchases not coded in GL | C22: 46295 | D22: -8420 | E22: GL adjustment | F22: =IF($C22="","",$B$4-$C22) -> 0 | G22: =IF($F22="","",IF($F22>Inputs!$C$9,"Aged","")) | H22: Journal: Dr 2310 / Cr 6160 - Financial Accountant | I22: 46297
A23: GST-02 | B23: Online sales cut-off difference between POS and GL | C23: 46295 | D23: 14300 | E23: Timing | F23: =IF($C23="","",$B$4-$C23) -> 0 | G23: =IF($F23="","",IF($F23>Inputs!$C$9,"Aged","")) | H23: Confirm in BAS review | I23: 46300
F24: =IF($C24="","",$B$4-$C24) | G24: =IF($F24="","",IF($F24>Inputs!$C$9,"Aged",""))
F25: =IF($C25="","",$B$4-$C25) | G25: =IF($F25="","",IF($F25>Inputs!$C$9,"Aged",""))
F26: =IF($C26="","",$B$4-$C26) | G26: =IF($F26="","",IF($F26>Inputs!$C$9,"Aged",""))
F27: =IF($C27="","",$B$4-$C27) | G27: =IF($F27="","",IF($F27>Inputs!$C$9,"Aged",""))
F28: =IF($C28="","",$B$4-$C28) | G28: =IF($F28="","",IF($F28>Inputs!$C$9,"Aged",""))
F29: =IF($C29="","",$B$4-$C29) | G29: =IF($F29="","",IF($F29>Inputs!$C$9,"Aged",""))
F30: =IF($C30="","",$B$4-$C30) | G30: =IF($F30="","",IF($F30>Inputs!$C$9,"Aged",""))
F31: =IF($C31="","",$B$4-$C31) | G31: =IF($F31="","",IF($F31>Inputs!$C$9,"Aged",""))
F32: =IF($C32="","",$B$4-$C32) | G32: =IF($F32="","",IF($F32>Inputs!$C$9,"Aged",""))
F33: =IF($C33="","",$B$4-$C33) | G33: =IF($F33="","",IF($F33>Inputs!$C$9,"Aged",""))
F34: =IF($C34="","",$B$4-$C34) | G34: =IF($F34="","",IF($F34>Inputs!$C$9,"Aged",""))
F35: =IF($C35="","",$B$4-$C35) | G35: =IF($F35="","",IF($F35>Inputs!$C$9,"Aged",""))
... F41: =IF($C41="","",$B$4-$C41) | G41: =IF($F41="","",IF($F41>Inputs!$C$9,"Aged",""))
A44: Sign-off
A45: Prepared by | B45: =Inputs!$C$6 -> Bhagyashree Amblimath | C45: 46300
A46: Reviewed by | B46: =Inputs!$C$7 -> Financial Controller (simulated) | D46: <- reviewer to date on sign-off
A48: Template notes: 'Timing' items clear on their own next period; 'GL adjustment' items need a journal. Source balance and items are simulated and hardcoded (blue); the difference must be nil.

Sheet Rec_Payroll
A1: Balance Sheet Reconciliation - Payroll liabilities (PAYG, super, accrued wages)
A2: =Inputs!$C$3 -> Specialty retailer (simulated, Adairs-style)
A4: Period end | B4: =Inputs!$C$5 -> 46295
A5: GL account 1 | B5: 2100 | C5: =INDEX(CoA!$B$6:$B$46,MATCH($B5,CoA!$A$6:$A$46,0)) -> PAYG withholding payable
A6: GL account 2 | B6: 2110 | C6: =INDEX(CoA!$B$6:$B$46,MATCH($B6,CoA!$A$6:$A$46,0)) -> Superannuation payable
A7: GL account 3 | B7: 2120 | C7: =INDEX(CoA!$B$6:$B$46,MATCH($B7,CoA!$A$6:$A$46,0)) -> Accrued wages
A8: Sign factor (1 = debit balance; -1 = credit balance shown positive) | B8: -1
A10: Balance per GL (TB closing) | D10: =$B$8*(IF($B$5="",0,SUMIF(TB!$A$6:$A$46,$B$5,TB!$F$6:$F$46))+IF($B$6="",0,SUMIF(TB!$A$6:$A$46,$B$6,TB!$F$6:$F$46))+IF($B$7="",0,SUMIF(TB!$A$6:$A$46,$B$7,TB!$F$6:$F$46))) -> 4595000
A11: Add / (less): GL adjustments (journals required) | D11: =SUMIF($E$22:$E$41,"GL adjustment",$D$22:$D$41) -> -96000
A12: Adjusted GL balance | D12: =D10+D11 -> 4499000
A14: Balance per source: | B14: Payroll system liabilities report | D14: 4454000
A15: Add / (less): timing items (clear next period) | D15: =SUMIF($E$22:$E$41,"Timing",$D$22:$D$41) -> 45000
A16: Adjusted source balance | D16: =D14+D15 -> 4499000
A18: Unreconciled difference (adjusted GL less adjusted source) | D18: =ROUND(D12-D16,2) -> 0 | E18: =IF(ABS(D18)<=Inputs!$C$12,"RECONCILED","INVESTIGATE") -> RECONCILED
A19: Items older than ageing threshold | D19: =COUNTIF($G$22:$G$41,"Aged") -> 0
A21: Ref | B21: Description of reconciling item | C21: Item date | D21: Amount ($) | E21: Type | F21: Days open | G21: Aged? | H21: Action / owner | I21: Expected clear
A22: PAY-01 | B22: Super contributions paid 29-Sep (SuperStream) not journalised | C22: 46294 | D22: -96000 | E22: GL adjustment | F22: =IF($C22="","",$B$4-$C22) -> 1 | G22: =IF($F22="","",IF($F22>Inputs!$C$9,"Aged","")) | H22: Journal: Dr 2110 / Cr 1000 - Payroll | I22: 46297
A23: PAY-02 | B23: Termination payout calculated 30-Sep, paid 2-Oct | C23: 46295 | D23: 45000 | E23: Timing | F23: =IF($C23="","",$B$4-$C23) -> 0 | G23: =IF($F23="","",IF($F23>Inputs!$C$9,"Aged","")) | H23: Clears 2-Oct - Payroll | I23: 46297
F24: =IF($C24="","",$B$4-$C24) | G24: =IF($F24="","",IF($F24>Inputs!$C$9,"Aged",""))
F25: =IF($C25="","",$B$4-$C25) | G25: =IF($F25="","",IF($F25>Inputs!$C$9,"Aged",""))
F26: =IF($C26="","",$B$4-$C26) | G26: =IF($F26="","",IF($F26>Inputs!$C$9,"Aged",""))
F27: =IF($C27="","",$B$4-$C27) | G27: =IF($F27="","",IF($F27>Inputs!$C$9,"Aged",""))
F28: =IF($C28="","",$B$4-$C28) | G28: =IF($F28="","",IF($F28>Inputs!$C$9,"Aged",""))
F29: =IF($C29="","",$B$4-$C29) | G29: =IF($F29="","",IF($F29>Inputs!$C$9,"Aged",""))
F30: =IF($C30="","",$B$4-$C30) | G30: =IF($F30="","",IF($F30>Inputs!$C$9,"Aged",""))
F31: =IF($C31="","",$B$4-$C31) | G31: =IF($F31="","",IF($F31>Inputs!$C$9,"Aged",""))
F32: =IF($C32="","",$B$4-$C32) | G32: =IF($F32="","",IF($F32>Inputs!$C$9,"Aged",""))
F33: =IF($C33="","",$B$4-$C33) | G33: =IF($F33="","",IF($F33>Inputs!$C$9,"Aged",""))
F34: =IF($C34="","",$B$4-$C34) | G34: =IF($F34="","",IF($F34>Inputs!$C$9,"Aged",""))
F35: =IF($C35="","",$B$4-$C35) | G35: =IF($F35="","",IF($F35>Inputs!$C$9,"Aged",""))
... F41: =IF($C41="","",$B$4-$C41) | G41: =IF($F41="","",IF($F41>Inputs!$C$9,"Aged",""))
A44: Sign-off
A45: Prepared by | B45: =Inputs!$C$6 -> Bhagyashree Amblimath | C45: 46300
A46: Reviewed by | B46: =Inputs!$C$7 -> Financial Controller (simulated) | D46: <- reviewer to date on sign-off
A48: Template notes: 'Timing' items clear on their own next period; 'GL adjustment' items need a journal. Source balance and items are simulated and hardcoded (blue); the difference must be nil.

Sheet Variance
A1: P&L Flux Analysis - Month Actual vs Budget vs Prior Year
A2: Presented with revenue positive; variances shown favourable / (unfavourable)
A3: Period end: | B3: =Inputs!$C$5 -> 46295
A5: Code | B5: Line | C5: Actual ($) | D5: Budget ($) | E5: Var vs budget ($) | F5: Var % | G5: Prior year ($) | H5: Var vs PY % | I5: Flag | J5: Commentary (drivers and actions)
A6: 4000 | B6: =INDEX(CoA!$B$6:$B$46,MATCH($A6,CoA!$A$6:$A$46,0)) -> Sales - stores | C6: =-INDEX(TB!$G$6:$G$46,MATCH($A6,TB!$A$6:$A$46,0)) -> 38200000 | D6: =-INDEX(TB!$H$6:$H$46,MATCH($A6,TB!$A$6:$A$46,0)) -> 37600000 | E6: =C6-D6 -> 600000 | F6: =IF(D6=0,0,E6/ABS(D6)) -> 0.015957447 | G6: =-INDEX(TB!$I$6:$I$46,MATCH($A6,TB!$A$6:$A$46,0)) -> 35100000 | H6: =IF(G6=0,0,(C6-G6)/ABS(G6)) -> 0.088319088 | I6: =IF(AND(ABS(E6)>=Inputs!$C$10,ABS(F6)>=Inputs!$C$11),"Explain","")
A7: 4010 | B7: =INDEX(CoA!$B$6:$B$46,MATCH($A7,CoA!$A$6:$A$46,0)) -> Sales - online | C7: =-INDEX(TB!$G$6:$G$46,MATCH($A7,TB!$A$6:$A$46,0)) -> 13900000 | D7: =-INDEX(TB!$H$6:$H$46,MATCH($A7,TB!$A$6:$A$46,0)) -> 14500000 | E7: =C7-D7 -> -600000 | F7: =IF(D7=0,0,E7/ABS(D7)) -> -0.04137931 | G7: =-INDEX(TB!$I$6:$I$46,MATCH($A7,TB!$A$6:$A$46,0)) -> 11200000 | H7: =IF(G7=0,0,(C7-G7)/ABS(G7)) -> 0.24107143 | I7: =IF(AND(ABS(E7)>=Inputs!$C$10,ABS(F7)>=Inputs!$C$11),"Explain","")
A8: 4900 | B8: =INDEX(CoA!$B$6:$B$46,MATCH($A8,CoA!$A$6:$A$46,0)) -> Sales returns and discounts | C8: =-INDEX(TB!$G$6:$G$46,MATCH($A8,TB!$A$6:$A$46,0)) -> -1950000 | D8: =-INDEX(TB!$H$6:$H$46,MATCH($A8,TB!$A$6:$A$46,0)) -> -1800000 | E8: =C8-D8 -> -150000 | F8: =IF(D8=0,0,E8/ABS(D8)) -> -0.083333333 | G8: =-INDEX(TB!$I$6:$I$46,MATCH($A8,TB!$A$6:$A$46,0)) -> -1700000 | H8: =IF(G8=0,0,(C8-G8)/ABS(G8)) -> -0.14705882 | I8: =IF(AND(ABS(E8)>=Inputs!$C$10,ABS(F8)>=Inputs!$C$11),"Explain","") -> Explain | J8: DRAFT. Returns and discounts $1.95m vs $1.80m budget: 3.7% of gross sales vs 3.5% budget and 3.7% prior year, so the rate is in line with last year but above plan. Confirm promotional discount depth with Retail. Credit note CN-4471 ($12.6k, AR-01) is not yet in the GL and will add to this line.
B9: Net sales | C9: =SUM(C6:C8) -> 50150000 | D9: =SUM(D6:D8) -> 50300000 | E9: =C9-D9 -> -150000 | F9: =IF(D9=0,0,E9/ABS(D9)) -> -0.0029821074 | G9: =SUM(G6:G8) -> 44600000 | H9: =IF(G9=0,0,(C9-G9)/ABS(G9)) -> 0.12443946 | I9: =IF(AND(ABS(E9)>=Inputs!$C$10,ABS(F9)>=Inputs!$C$11),"Explain","")
A10: 5000 | B10: =INDEX(CoA!$B$6:$B$46,MATCH($A10,CoA!$A$6:$A$46,0)) -> Cost of goods sold | C10: =INDEX(TB!$G$6:$G$46,MATCH($A10,TB!$A$6:$A$46,0)) -> 19600000 | D10: =INDEX(TB!$H$6:$H$46,MATCH($A10,TB!$A$6:$A$46,0)) -> 19300000 | E10: =D10-C10 -> -300000 | F10: =IF(D10=0,0,E10/ABS(D10)) -> -0.015544041 | G10: =INDEX(TB!$I$6:$I$46,MATCH($A10,TB!$A$6:$A$46,0)) -> 18200000 | H10: =IF(G10=0,0,(G10-C10)/ABS(G10)) -> -0.076923077 | I10: =IF(AND(ABS(E10)>=Inputs!$C$10,ABS(F10)>=Inputs!$C$11),"Explain","")
A11: 5010 | B11: =INDEX(CoA!$B$6:$B$46,MATCH($A11,CoA!$A$6:$A$46,0)) -> Freight inwards | C11: =INDEX(TB!$G$6:$G$46,MATCH($A11,TB!$A$6:$A$46,0)) -> 1700000 | D11: =INDEX(TB!$H$6:$H$46,MATCH($A11,TB!$A$6:$A$46,0)) -> 1600000 | E11: =D11-C11 -> -100000 | F11: =IF(D11=0,0,E11/ABS(D11)) -> -0.0625 | G11: =INDEX(TB!$I$6:$I$46,MATCH($A11,TB!$A$6:$A$46,0)) -> 1450000 | H11: =IF(G11=0,0,(G11-C11)/ABS(G11)) -> -0.17241379 | I11: =IF(AND(ABS(E11)>=Inputs!$C$10,ABS(F11)>=Inputs!$C$11),"Explain","") -> Explain | J11: DRAFT. Freight inwards $0.10m (6%) over budget; 3.4% of net sales vs 3.2% budget. Likely inbound container rates and online parcel mix. Confirm with Supply Chain whether the rate is a one-off or run-rate before the forecast refresh.
A12: 5020 | B12: =INDEX(CoA!$B$6:$B$46,MATCH($A12,CoA!$A$6:$A$46,0)) -> Inventory shrinkage and provisions | C12: =INDEX(TB!$G$6:$G$46,MATCH($A12,TB!$A$6:$A$46,0)) -> 420000 | D12: =INDEX(TB!$H$6:$H$46,MATCH($A12,TB!$A$6:$A$46,0)) -> 350000 | E12: =D12-C12 -> -70000 | F12: =IF(D12=0,0,E12/ABS(D12)) -> -0.2 | G12: =INDEX(TB!$I$6:$I$46,MATCH($A12,TB!$A$6:$A$46,0)) -> 330000 | H12: =IF(G12=0,0,(G12-C12)/ABS(G12)) -> -0.27272727 | I12: =IF(AND(ABS(E12)>=Inputs!$C$10,ABS(F12)>=Inputs!$C$11),"Explain","") | J12: DRAFT. Shrinkage $70k over budget, below the explain threshold. Q1 cycle count variance of $265k (INV-01) is not yet posted; once journalled shrinkage becomes about $685k vs $350k budget and will need explanation. Supply Chain Finance to confirm store split.
B13: Total cost of goods sold | C13: =SUM(C10:C12) -> 21720000 | D13: =SUM(D10:D12) -> 21250000 | E13: =D13-C13 -> -470000 | F13: =IF(D13=0,0,E13/ABS(D13)) -> -0.022117647 | G13: =SUM(G10:G12) -> 19980000 | H13: =IF(G13=0,0,(G13-C13)/ABS(G13)) -> -0.087087087 | I13: =IF(AND(ABS(E13)>=Inputs!$C$10,ABS(F13)>=Inputs!$C$11),"Explain","")
B14: Gross profit | C14: =C9-C13 -> 28430000 | D14: =D9-D13 -> 29050000 | E14: =C14-D14 -> -620000 | F14: =IF(D14=0,0,E14/ABS(D14)) -> -0.021342513 | G14: =G9-G13 -> 24620000 | H14: =IF(G14=0,0,(C14-G14)/ABS(G14)) -> 0.15475223 | I14: =IF(AND(ABS(E14)>=Inputs!$C$10,ABS(F14)>=Inputs!$C$11),"Explain","")
B15: Gross margin % | C15: =IF(C9=0,0,C14/C9) -> 0.5668993 | D15: =IF(D9=0,0,D14/D9) -> 0.57753479 | G15: =IF(G9=0,0,G14/G9) -> 0.55201794
A16: 6000 | B16: =INDEX(CoA!$B$6:$B$46,MATCH($A16,CoA!$A$6:$A$46,0)) -> Wages and salaries - stores | C16: =INDEX(TB!$G$6:$G$46,MATCH($A16,TB!$A$6:$A$46,0)) -> 8900000 | D16: =INDEX(TB!$H$6:$H$46,MATCH($A16,TB!$A$6:$A$46,0)) -> 8700000 | E16: =D16-C16 -> -200000 | F16: =IF(D16=0,0,E16/ABS(D16)) -> -0.022988506 | G16: =INDEX(TB!$I$6:$I$46,MATCH($A16,TB!$A$6:$A$46,0)) -> 8100000 | H16: =IF(G16=0,0,(G16-C16)/ABS(G16)) -> -0.098765432 | I16: =IF(AND(ABS(E16)>=Inputs!$C$10,ABS(F16)>=Inputs!$C$11),"Explain","")
A17: 6010 | B17: =INDEX(CoA!$B$6:$B$46,MATCH($A17,CoA!$A$6:$A$46,0)) -> Wages and salaries - head office | C17: =INDEX(TB!$G$6:$G$46,MATCH($A17,TB!$A$6:$A$46,0)) -> 3100000 | D17: =INDEX(TB!$H$6:$H$46,MATCH($A17,TB!$A$6:$A$46,0)) -> 3050000 | E17: =D17-C17 -> -50000 | F17: =IF(D17=0,0,E17/ABS(D17)) -> -0.016393443 | G17: =INDEX(TB!$I$6:$I$46,MATCH($A17,TB!$A$6:$A$46,0)) -> 2800000 | H17: =IF(G17=0,0,(G17-C17)/ABS(G17)) -> -0.10714286 | I17: =IF(AND(ABS(E17)>=Inputs!$C$10,ABS(F17)>=Inputs!$C$11),"Explain","")
A18: 6020 | B18: =INDEX(CoA!$B$6:$B$46,MATCH($A18,CoA!$A$6:$A$46,0)) -> Superannuation expense | C18: =INDEX(TB!$G$6:$G$46,MATCH($A18,TB!$A$6:$A$46,0)) -> 1440000 | D18: =INDEX(TB!$H$6:$H$46,MATCH($A18,TB!$A$6:$A$46,0)) -> 1410000 | E18: =D18-C18 -> -30000 | F18: =IF(D18=0,0,E18/ABS(D18)) -> -0.021276596 | G18: =INDEX(TB!$I$6:$I$46,MATCH($A18,TB!$A$6:$A$46,0)) -> 1260000 | H18: =IF(G18=0,0,(G18-C18)/ABS(G18)) -> -0.14285714 | I18: =IF(AND(ABS(E18)>=Inputs!$C$10,ABS(F18)>=Inputs!$C$11),"Explain","")
A19: 6100 | B19: =INDEX(CoA!$B$6:$B$46,MATCH($A19,CoA!$A$6:$A$46,0)) -> Rent and occupancy | C19: =INDEX(TB!$G$6:$G$46,MATCH($A19,TB!$A$6:$A$46,0)) -> 4300000 | D19: =INDEX(TB!$H$6:$H$46,MATCH($A19,TB!$A$6:$A$46,0)) -> 4300000 | E19: =D19-C19 -> 0 | F19: =IF(D19=0,0,E19/ABS(D19)) -> 0 | G19: =INDEX(TB!$I$6:$I$46,MATCH($A19,TB!$A$6:$A$46,0)) -> 4050000 | H19: =IF(G19=0,0,(G19-C19)/ABS(G19)) -> -0.061728395 | I19: =IF(AND(ABS(E19)>=Inputs!$C$10,ABS(F19)>=Inputs!$C$11),"Explain","")
A20: 6110 | B20: =INDEX(CoA!$B$6:$B$46,MATCH($A20,CoA!$A$6:$A$46,0)) -> Marketing | C20: =INDEX(TB!$G$6:$G$46,MATCH($A20,TB!$A$6:$A$46,0)) -> 3350000 | D20: =INDEX(TB!$H$6:$H$46,MATCH($A20,TB!$A$6:$A$46,0)) -> 3000000 | E20: =D20-C20 -> -350000 | F20: =IF(D20=0,0,E20/ABS(D20)) -> -0.11666667 | G20: =INDEX(TB!$I$6:$I$46,MATCH($A20,TB!$A$6:$A$46,0)) -> 2700000 | H20: =IF(G20=0,0,(G20-C20)/ABS(G20)) -> -0.24074074 | I20: =IF(AND(ABS(E20)>=Inputs!$C$10,ABS(F20)>=Inputs!$C$11),"Explain","") -> Explain | J20: DRAFT. Marketing $350k (12%) over budget at 6.7% of net sales vs 6.0% budget, while online sales finished $600k (4%) under budget. Spend has not converted to plan. Ask Marketing for campaign-level return and whether the overspend is phasing or incremental.
A21: 6130 | B21: =INDEX(CoA!$B$6:$B$46,MATCH($A21,CoA!$A$6:$A$46,0)) -> IT and software | C21: =INDEX(TB!$G$6:$G$46,MATCH($A21,TB!$A$6:$A$46,0)) -> 780000 | D21: =INDEX(TB!$H$6:$H$46,MATCH($A21,TB!$A$6:$A$46,0)) -> 720000 | E21: =D21-C21 -> -60000 | F21: =IF(D21=0,0,E21/ABS(D21)) -> -0.083333333 | G21: =INDEX(TB!$I$6:$I$46,MATCH($A21,TB!$A$6:$A$46,0)) -> 650000 | H21: =IF(G21=0,0,(G21-C21)/ABS(G21)) -> -0.2 | I21: =IF(AND(ABS(E21)>=Inputs!$C$10,ABS(F21)>=Inputs!$C$11),"Explain","")
A22: 6140 | B22: =INDEX(CoA!$B$6:$B$46,MATCH($A22,CoA!$A$6:$A$46,0)) -> Utilities | C22: =INDEX(TB!$G$6:$G$46,MATCH($A22,TB!$A$6:$A$46,0)) -> 410000 | D22: =INDEX(TB!$H$6:$H$46,MATCH($A22,TB!$A$6:$A$46,0)) -> 400000 | E22: =D22-C22 -> -10000 | F22: =IF(D22=0,0,E22/ABS(D22)) -> -0.025 | G22: =INDEX(TB!$I$6:$I$46,MATCH($A22,TB!$A$6:$A$46,0)) -> 380000 | H22: =IF(G22=0,0,(G22-C22)/ABS(G22)) -> -0.078947368 | I22: =IF(AND(ABS(E22)>=Inputs!$C$10,ABS(F22)>=Inputs!$C$11),"Explain","")
A23: 6150 | B23: =INDEX(CoA!$B$6:$B$46,MATCH($A23,CoA!$A$6:$A$46,0)) -> Bank and merchant fees | C23: =INDEX(TB!$G$6:$G$46,MATCH($A23,TB!$A$6:$A$46,0)) -> 690000 | D23: =INDEX(TB!$H$6:$H$46,MATCH($A23,TB!$A$6:$A$46,0)) -> 650000 | E23: =D23-C23 -> -40000 | F23: =IF(D23=0,0,E23/ABS(D23)) -> -0.061538462 | G23: =INDEX(TB!$I$6:$I$46,MATCH($A23,TB!$A$6:$A$46,0)) -> 560000 | H23: =IF(G23=0,0,(G23-C23)/ABS(G23)) -> -0.23214286 | I23: =IF(AND(ABS(E23)>=Inputs!$C$10,ABS(F23)>=Inputs!$C$11),"Explain","")
A24: 6160 | B24: =INDEX(CoA!$B$6:$B$46,MATCH($A24,CoA!$A$6:$A$46,0)) -> Other operating expenses | C24: =INDEX(TB!$G$6:$G$46,MATCH($A24,TB!$A$6:$A$46,0)) -> 1050000 | D24: =INDEX(TB!$H$6:$H$46,MATCH($A24,TB!$A$6:$A$46,0)) -> 1000000 | E24: =D24-C24 -> -50000 | F24: =IF(D24=0,0,E24/ABS(D24)) -> -0.05 | G24: =INDEX(TB!$I$6:$I$46,MATCH($A24,TB!$A$6:$A$46,0)) -> 920000 | H24: =IF(G24=0,0,(G24-C24)/ABS(G24)) -> -0.14130435 | I24: =IF(AND(ABS(E24)>=Inputs!$C$10,ABS(F24)>=Inputs!$C$11),"Explain","")
B25: Total operating expenses (before depreciation) | C25: =SUM(C16:C24) -> 24020000 | D25: =SUM(D16:D24) -> 23230000 | E25: =D25-C25 -> -790000 | F25: =IF(D25=0,0,E25/ABS(D25)) -> -0.034007749 | G25: =SUM(G16:G24) -> 21420000 | H25: =IF(G25=0,0,(G25-C25)/ABS(G25)) -> -0.12138189 | I25: =IF(AND(ABS(E25)>=Inputs!$C$10,ABS(F25)>=Inputs!$C$11),"Explain","")
B26: EBITDA | C26: =C14-C25 -> 4410000 | D26: =D14-D25 -> 5820000 | E26: =C26-D26 -> -1410000 | F26: =IF(D26=0,0,E26/ABS(D26)) -> -0.24226804 | G26: =G14-G25 -> 3200000 | H26: =IF(G26=0,0,(C26-G26)/ABS(G26)) -> 0.378125 | I26: =IF(AND(ABS(E26)>=Inputs!$C$10,ABS(F26)>=Inputs!$C$11),"Explain","") -> Explain | J26: DRAFT. EBITDA $1.41m (24%) below budget. Gross profit is $0.62m short (net sales $0.15m under and gross margin 56.7% vs 57.8% budget) and operating expenses $0.79m over, led by marketing ($350k) and store wages ($200k). Up 38% on prior year on 12% sales growth.
A27: 6120 | B27: =INDEX(CoA!$B$6:$B$46,MATCH($A27,CoA!$A$6:$A$46,0)) -> Depreciation | C27: =INDEX(TB!$G$6:$G$46,MATCH($A27,TB!$A$6:$A$46,0)) -> 1650000 | D27: =INDEX(TB!$H$6:$H$46,MATCH($A27,TB!$A$6:$A$46,0)) -> 1600000 | E27: =D27-C27 -> -50000 | F27: =IF(D27=0,0,E27/ABS(D27)) -> -0.03125 | G27: =INDEX(TB!$I$6:$I$46,MATCH($A27,TB!$A$6:$A$46,0)) -> 1500000 | H27: =IF(G27=0,0,(G27-C27)/ABS(G27)) -> -0.1 | I27: =IF(AND(ABS(E27)>=Inputs!$C$10,ABS(F27)>=Inputs!$C$11),"Explain","")
B28: EBIT | C28: =C26-C27 -> 2760000 | D28: =D26-D27 -> 4220000 | E28: =C28-D28 -> -1460000 | F28: =IF(D28=0,0,E28/ABS(D28)) -> -0.34597156 | G28: =G26-G27 -> 1700000 | H28: =IF(G28=0,0,(C28-G28)/ABS(G28)) -> 0.62352941 | I28: =IF(AND(ABS(E28)>=Inputs!$C$10,ABS(F28)>=Inputs!$C$11),"Explain","") -> Explain | J28: DRAFT. EBIT $1.46m below budget; the EBITDA shortfall plus depreciation $50k over budget, in line with $2.1m of September additions (FA_Register).
A29: 7000 | B29: =INDEX(CoA!$B$6:$B$46,MATCH($A29,CoA!$A$6:$A$46,0)) -> Interest expense | C29: =INDEX(TB!$G$6:$G$46,MATCH($A29,TB!$A$6:$A$46,0)) -> 640000 | D29: =INDEX(TB!$H$6:$H$46,MATCH($A29,TB!$A$6:$A$46,0)) -> 650000 | E29: =D29-C29 -> 10000 | F29: =IF(D29=0,0,E29/ABS(D29)) -> 0.015384615 | G29: =INDEX(TB!$I$6:$I$46,MATCH($A29,TB!$A$6:$A$46,0)) -> 700000 | H29: =IF(G29=0,0,(G29-C29)/ABS(G29)) -> 0.085714286 | I29: =IF(AND(ABS(E29)>=Inputs!$C$10,ABS(F29)>=Inputs!$C$11),"Explain","")
B30: Net profit before tax | C30: =C28-C29 -> 2120000 | D30: =D28-D29 -> 3570000 | E30: =C30-D30 -> -1450000 | F30: =IF(D30=0,0,E30/ABS(D30)) -> -0.40616246 | G30: =G28-G29 -> 1000000 | H30: =IF(G30=0,0,(C30-G30)/ABS(G30)) -> 1.12 | I30: =IF(AND(ABS(E30)>=Inputs!$C$10,ABS(F30)>=Inputs!$C$11),"Explain","") -> Explain | J30: DRAFT. NPBT $2.12m vs $3.57m budget and $1.00m prior year. This is pre-journal: the GL adjustments on Rec_Summary (merchant fees, cycle count, rent accrual reversal, insurance, GST coding, CN-4471) net to about a $0.13m reduction in NPBT, before coding of AP-01 ($31k).
A32: Flag logic: 'Explain' appears when the variance to budget exceeds BOTH the $ and % thresholds on the Inputs tab. Commentary cells (yellow) are for the preparer to complete.

Sheet FA_Register
A1: Fixed Asset Register and Roll-Forward
A2: Month movement ties to the TB, the P&L depreciation charge and the BAS capital purchases
A3: Period end | C3: =Inputs!$C$5 -> 46295
A4: Tax rate for deferred tax | C4: 0.3 | D4: Simulated input; use the entity's applicable corporate tax rate
A6: Asset ID | B6: Description | C6: Class | D6: GL cost a/c | E6: GL acc dep a/c | F6: Life (months) | G6: Opening cost ($) | H6: Additions ($) | I6: Disposals - cost ($) | J6: Closing cost ($) | K6: Opening acc dep ($) | L6: Depreciation ($) | M6: Acc dep on disposals ($) | N6: Closing acc dep ($) | O6: Closing NBV ($) | P6: Tax rate % pa | Q6: Opening tax WDV ($) | R6: Tax depreciation ($) | S6: Closing tax WDV ($) | T6: Temporary difference ($)
A7: FA-001 | B7: Metro store fit-outs | C7: Fit-out | D7: 1500 | E7: 1510 | F7: 120 | G7: 61300000 | H7: 700000 | I7: 0 | J7: =IF($A7="","",G7+H7-I7) -> 62000000 | K7: 28500000 | L7: =IF($A7="","",IF(F7=0,0,MAX(0,MIN(J7/F7,J7-K7+M7)))) -> 516666.67 | M7: 0 | N7: =IF($A7="","",K7+L7-M7) -> 29016667 | O7: =IF($A7="","",J7-N7) -> 32983333 | P7: 0.12 | Q7: 30100000 | R7: =IF($A7="","",(Q7+H7)*P7/12) -> 308000 | S7: =IF($A7="","",Q7+H7-R7) -> 30492000 | T7: =IF($A7="","",O7-S7) -> 2491333.3
A8: FA-002 | B8: Regional store fit-outs | C8: Fit-out | D8: 1500 | E8: 1510 | F8: 120 | G8: 47500000 | H8: 500000 | I8: 0 | J8: =IF($A8="","",G8+H8-I8) -> 48000000 | K8: 25000000 | L8: =IF($A8="","",IF(F8=0,0,MAX(0,MIN(J8/F8,J8-K8+M8)))) -> 400000 | M8: 0 | N8: =IF($A8="","",K8+L8-M8) -> 25400000 | O8: =IF($A8="","",J8-N8) -> 22600000 | P8: 0.12 | Q8: 20400000 | R8: =IF($A8="","",(Q8+H8)*P8/12) -> 209000 | S8: =IF($A8="","",Q8+H8-R8) -> 20691000 | T8: =IF($A8="","",O8-S8) -> 1909000
A9: FA-003 | B9: Distribution centre racking and automation | C9: Fit-out | D9: 1500 | E9: 1510 | F9: 120 | G9: 33900000 | H9: 100000 | I9: 0 | J9: =IF($A9="","",G9+H9-I9) -> 34000000 | K9: 16500000 | L9: =IF($A9="","",IF(F9=0,0,MAX(0,MIN(J9/F9,J9-K9+M9)))) -> 283333.33 | M9: 0 | N9: =IF($A9="","",K9+L9-M9) -> 16783333 | O9: =IF($A9="","",J9-N9) -> 17216667 | P9: 0.12 | Q9: 15000000 | R9: =IF($A9="","",(Q9+H9)*P9/12) -> 151000 | S9: =IF($A9="","",Q9+H9-R9) -> 14949000 | T9: =IF($A9="","",O9-S9) -> 2267666.7
A10: FA-004 | B10: Capital work in progress: new store fit-outs (not depreciated) | C10: Fit-out | D10: 1500 | E10: 1510 | F10: 0 | G10: 3600000 | H10: 400000 | I10: 0 | J10: =IF($A10="","",G10+H10-I10) -> 4000000 | K10: 0 | L10: =IF($A10="","",IF(F10=0,0,MAX(0,MIN(J10/F10,J10-K10+M10)))) -> 0 | M10: 0 | N10: =IF($A10="","",K10+L10-M10) -> 0 | O10: =IF($A10="","",J10-N10) -> 4000000 | P10: 0 | Q10: 3600000 | R10: =IF($A10="","",(Q10+H10)*P10/12) -> 0 | S10: =IF($A10="","",Q10+H10-R10) -> 4000000 | T10: =IF($A10="","",O10-S10) -> 0
A11: FA-101 | B11: POS and store hardware | C11: IT | D11: 1505 | E11: 1515 | F11: 36 | G11: 8000000 | H11: 250000 | I11: 0 | J11: =IF($A11="","",G11+H11-I11) -> 8250000 | K11: 6500000 | L11: =IF($A11="","",IF(F11=0,0,MAX(0,MIN(J11/F11,J11-K11+M11)))) -> 229166.67 | M11: 0 | N11: =IF($A11="","",K11+L11-M11) -> 6729166.7 | O11: =IF($A11="","",J11-N11) -> 1520833.3 | P11: 0.3 | Q11: 1100000 | R11: =IF($A11="","",(Q11+H11)*P11/12) -> 33750 | S11: =IF($A11="","",Q11+H11-R11) -> 1316250 | T11: =IF($A11="","",O11-S11) -> 204583.33
A12: FA-102 | B12: Servers, network and infrastructure | C12: IT | D12: 1505 | E12: 1515 | F12: 60 | G12: 13100000 | H12: 150000 | I12: 0 | J12: =IF($A12="","",G12+H12-I12) -> 13250000 | K12: 6450000 | L12: =IF($A12="","",IF(F12=0,0,MAX(0,MIN(J12/F12,J12-K12+M12)))) -> 220833.33 | M12: 0 | N12: =IF($A12="","",K12+L12-M12) -> 6670833.3 | O12: =IF($A12="","",J12-N12) -> 6579166.7 | P12: 0.2 | Q12: 5200000 | R12: =IF($A12="","",(Q12+H12)*P12/12) -> 89166.667 | S12: =IF($A12="","",Q12+H12-R12) -> 5260833.3 | T12: =IF($A12="","",O12-S12) -> 1318333.3
J13: =IF($A13="","",G13+H13-I13) | L13: =IF($A13="","",IF(F13=0,0,MAX(0,MIN(J13/F13,J13-K13+M13)))) | N13: =IF($A13="","",K13+L13-M13) | O13: =IF($A13="","",J13-N13) | R13: =IF($A13="","",(Q13+H13)*P13/12) | S13: =IF($A13="","",Q13+H13-R13) | T13: =IF($A13="","",O13-S13)
J14: =IF($A14="","",G14+H14-I14) | L14: =IF($A14="","",IF(F14=0,0,MAX(0,MIN(J14/F14,J14-K14+M14)))) | N14: =IF($A14="","",K14+L14-M14) | O14: =IF($A14="","",J14-N14) | R14: =IF($A14="","",(Q14+H14)*P14/12) | S14: =IF($A14="","",Q14+H14-R14) | T14: =IF($A14="","",O14-S14)
J15: =IF($A15="","",G15+H15-I15) | L15: =IF($A15="","",IF(F15=0,0,MAX(0,MIN(J15/F15,J15-K15+M15)))) | N15: =IF($A15="","",K15+L15-M15) | O15: =IF($A15="","",J15-N15) | R15: =IF($A15="","",(Q15+H15)*P15/12) | S15: =IF($A15="","",Q15+H15-R15) | T15: =IF($A15="","",O15-S15)
J16: =IF($A16="","",G16+H16-I16) | L16: =IF($A16="","",IF(F16=0,0,MAX(0,MIN(J16/F16,J16-K16+M16)))) | N16: =IF($A16="","",K16+L16-M16) | O16: =IF($A16="","",J16-N16) | R16: =IF($A16="","",(Q16+H16)*P16/12) | S16: =IF($A16="","",Q16+H16-R16) | T16: =IF($A16="","",O16-S16)
B17: Total | G17: =SUM(G7:G16) -> 167400000 | H17: =SUM(H7:H16) -> 2100000 | I17: =SUM(I7:I16) -> 0 | J17: =SUM(J7:J16) -> 169500000 | K17: =SUM(K7:K16) -> 82950000 | L17: =SUM(L7:L16) -> 1650000 | M17: =SUM(M7:M16) -> 0 | N17: =SUM(N7:N16) -> 84600000 | O17: =SUM(O7:O16) -> 84900000 | Q17: =SUM(Q7:Q16) -> 75400000 | R17: =SUM(R7:R16) -> 790916.67 | S17: =SUM(S7:S16) -> 76709083 | T17: =SUM(T7:T16) -> 8190916.7
B19: GL tie-out
B20: Tie-out | C20: GL account(s) | D20: Per register ($) | E20: Per GL ($) | F20: Difference ($) | G20: Status
B21: Closing cost: fit-out | C21: 1500 | D21: =SUMIF($C$7:$C$16,"Fit-out",$J$7:$J$16) -> 148000000 | E21: =SUMIF(TB!$A$6:$A$46,1500,TB!$F$6:$F$46) -> 148000000 | F21: =ROUND(D21-E21,2) -> 0 | G21: =IF(ABS(F21)<=Inputs!$C$12,"TIES","INVESTIGATE") -> TIES
B22: Closing cost: IT equipment | C22: 1505 | D22: =SUMIF($C$7:$C$16,"IT",$J$7:$J$16) -> 21500000 | E22: =SUMIF(TB!$A$6:$A$46,1505,TB!$F$6:$F$46) -> 21500000 | F22: =ROUND(D22-E22,2) -> 0 | G22: =IF(ABS(F22)<=Inputs!$C$12,"TIES","INVESTIGATE") -> TIES
B23: Closing accumulated depreciation: fit-out | C23: 1510 | D23: =SUMIF($C$7:$C$16,"Fit-out",$N$7:$N$16) -> 71200000 | E23: =-SUMIF(TB!$A$6:$A$46,1510,TB!$F$6:$F$46) -> 71200000 | F23: =ROUND(D23-E23,2) -> 0 | G23: =IF(ABS(F23)<=Inputs!$C$12,"TIES","INVESTIGATE") -> TIES
B24: Closing accumulated depreciation: IT equipment | C24: 1515 | D24: =SUMIF($C$7:$C$16,"IT",$N$7:$N$16) -> 13400000 | E24: =-SUMIF(TB!$A$6:$A$46,1515,TB!$F$6:$F$46) -> 13400000 | F24: =ROUND(D24-E24,2) -> 0 | G24: =IF(ABS(F24)<=Inputs!$C$12,"TIES","INVESTIGATE") -> TIES
B25: Opening cost vs prior month TB | C25: 1500 + 1505 | D25: =G17 -> 167400000 | E25: =SUMIF(TB!$A$6:$A$46,1500,TB!$E$6:$E$46)+SUMIF(TB!$A$6:$A$46,1505,TB!$E$6:$E$46) -> 167400000 | F25: =ROUND(D25-E25,2) -> 0 | G25: =IF(ABS(F25)<=Inputs!$C$12,"TIES","INVESTIGATE") -> TIES
B26: Opening accumulated depreciation vs prior month TB | C26: 1510 + 1515 | D26: =K17 -> 82950000 | E26: =-(SUMIF(TB!$A$6:$A$46,1510,TB!$E$6:$E$46)+SUMIF(TB!$A$6:$A$46,1515,TB!$E$6:$E$46)) -> 82950000 | F26: =ROUND(D26-E26,2) -> 0 | G26: =IF(ABS(F26)<=Inputs!$C$12,"TIES","INVESTIGATE") -> TIES
B27: Additions: fit-out vs TB movement | C27: 1500 | D27: =SUMIF($C$7:$C$16,"Fit-out",$H$7:$H$16) -> 1700000 | E27: =SUMIF(TB!$A$6:$A$46,1500,TB!$G$6:$G$46) -> 1700000 | F27: =ROUND(D27-E27,2) -> 0 | G27: =IF(ABS(F27)<=Inputs!$C$12,"TIES","INVESTIGATE") -> TIES
B28: Additions: IT equipment vs TB movement | C28: 1505 | D28: =SUMIF($C$7:$C$16,"IT",$H$7:$H$16) -> 400000 | E28: =SUMIF(TB!$A$6:$A$46,1505,TB!$G$6:$G$46) -> 400000 | F28: =ROUND(D28-E28,2) -> 0 | G28: =IF(ABS(F28)<=Inputs!$C$12,"TIES","INVESTIGATE") -> TIES
B29: Depreciation charge vs P&L | C29: 6120 | D29: =L17 -> 1650000 | E29: =SUMIF(TB!$A$6:$A$46,6120,TB!$G$6:$G$46) -> 1650000 | F29: =ROUND(D29-E29,2) -> 0 | G29: =IF(ABS(F29)<=Inputs!$C$12,"TIES","INVESTIGATE") -> TIES
B30: Additions vs BAS capital purchases (ex GST) | C30: BAS_IAS G10 | D30: =H17 -> 2100000 | E30: =BAS_IAS!D17/(1+BAS_IAS!$D$5) -> 2100000 | F30: =ROUND(D30-E30,2) -> 0 | G30: =IF(ABS(F30)<=Inputs!$C$12,"TIES","INVESTIGATE") -> TIES
B31: Sum of absolute differences | F31: =SUMPRODUCT(ABS(F21:F30)) -> 0
B33: Net book value roll-forward
B34: Opening NBV | D34: =G17-K17 -> 84450000
B35: Add: additions | D35: =H17 -> 2100000
B36: Less: depreciation | D36: =-L17 -> -1650000
B37: Less: NBV of disposals | D37: =-(I17-M17) -> 0
B38: Closing NBV | D38: =SUM(D34:D37) -> 84900000
B39: Check: agrees to register closing NBV (difference) | D39: =ROUND(D38-O17,2) -> 0 | E39: =IF(D39=0,"OK","Review") -> OK
B41: Book vs tax (informational)
B42: Closing book NBV | D42: =O17 -> 84900000
B43: Closing tax written-down value | D43: =S17 -> 76709083
B44: Taxable temporary difference | D44: =D42-D43 -> 8190916.7
B45: Deferred tax liability on the difference | D45: =D44*$C$4 -> 2457275
B47: Notes and conventions
B48: 1. Straight-line depreciation on closing cost, full month charged in the month of addition; capped so NBV never goes below nil.
B49: 2. Capital work in progress (life 0) is not depreciated until transferred to a depreciating class.
B50: 3. No disposals this month; disposal columns are in place and flow through the roll-forward. BAS G10 assumes no disposals.
B51: 4. Tax depreciation is a simplified diminishing-value illustration on simulated rates, not ATO effective-life or instant asset write-off treatment.
B52: 5. The deferred tax liability is informational: the simulated TB has no deferred tax accounts.
B53: 6. All asset balances, lives and tax rates are simulated and chosen so the register ties to the simulated TB.
B55: Sign-off
B56: Prepared by | C56: =Inputs!$C$6 -> Bhagyashree Amblimath | G56: 46300
B57: Reviewed by | C57: =Inputs!$C$7 -> Financial Controller (simulated)

Sheet BAS_IAS
A1: Business Activity Statement (monthly) and IAS Workings
A2: =Inputs!$C$3 -> Specialty retailer (simulated, Adairs-style)
A3: Period end | D3: =Inputs!$C$5 -> 46295
A4: Lodgement and payment due | D4: =DATE(YEAR(D3),MONTH(D3)+1,21) -> 46316 | E4: Monthly lodgers: 21st of the following month. Confirm against ATO key dates (weekends, concessions).
A5: GST rate | D5: =Inputs!$C$8 -> 0.1
A7: Ref | B7: Taxable sales reconciliation | C7: Source / basis | D7: Amount ($)
A8: S1 | B8: Net sales per P&L (ex GST) | C8: Variance tab, net sales actual | D8: =Variance!C9 -> 50150000
A9: S2 | B9: Less: online orders dispatched after midnight 30-Sep (GST attributed to October) | C9: Simulated cut-off item; flows to Rec_GST timing item | D9: -143000
A10: S3 | B10: Less: GST-free and input-taxed sales | C10: None assumed for homewares retail (simulated) | D10: 0
A11: S4 | B11: Taxable sales (ex GST) | D11: =D8+D9-D10 -> 50007000
A13: BAS label | B13: Description | C13: Source / basis | D13: Amount ($)
A14: G1 | B14: Total sales and other income (incl GST) | C14: Taxable sales x (1 + GST rate) + GST-free sales | D14: =D11*(1+$D$5)+D10 -> 55007700
A15: G2 | B15: Export sales | C15: None (simulated) | D15: 0
A16: G3 | B16: Other GST-free sales | C16: From S3 | D16: =D10 -> 0
A17: G10 | B17: Capital purchases (incl GST) | C17: Cost additions per TB movement (1500, 1505) x (1 + rate); assumes no disposals | D17: =(SUMIF(TB!$A$6:$A$46,1500,TB!$G$6:$G$46)+SUMIF(TB!$A$6:$A$46,1505,TB!$G$6:$G$46))*(1+$D$5) -> 2310000
A18: G11 | B18: Non-capital purchases (incl GST) | C18: Creditable purchases ex GST (input below) x (1 + rate) | D18: =D19*(1+$D$5) -> 23632620
A19: Input | B19: Creditable non-capital purchases (ex GST) | C19: Simulated AP / GL purchases report; replace with extract | D19: 21484200
A21: 1A | B21: GST on sales | C21: (G1 - G2 - G3) x rate / (1 + rate) | D21: =ROUND((D14-D15-D16)*$D$5/(1+$D$5),0) -> 5000700
A22: 1B | B22: GST on purchases (input tax credits) | C22: (G10 + G11) x rate / (1 + rate) | D22: =ROUND((D17+D18)*$D$5/(1+$D$5),0) -> 2358420
B23: Net GST payable (1A less 1B) | D23: =D21-D22 -> 2642280
A24: W1 | B24: Total salary, wages and other payments | C24: Wages expense (6000 + 6010) less non-cash increases in accrued wages (2120) and leave provision (2130) | D24: =SUMIF(TB!$A$6:$A$46,6000,TB!$G$6:$G$46)+SUMIF(TB!$A$6:$A$46,6010,TB!$G$6:$G$46)+SUMIF(TB!$A$6:$A$46,2120,TB!$G$6:$G$46)+SUMIF(TB!$A$6:$A$46,2130,TB!$G$6:$G$46) -> 11800000
A25: W2 | B25: Amount withheld from payments | C25: PAYG withholding payable per GL (2100); prior month assumed remitted | D25: =-SUMIF(TB!$A$6:$A$46,2100,TB!$F$6:$F$46) -> 1950000
B26: Total payable to ATO (net GST + PAYG withholding) | D26: =D23+D25 -> 4592280
A27: Illustrative summary: confirm field mapping and any other labels (e.g. PAYG instalments) against the current ATO BAS form before lodgement.
A29: Ref | B29: BAS to GL reconciliation | C29: Explanation of difference | D29: Per GL ($) | E29: Per BAS ($) | F29: Difference ($) | G29: Explained ($) | H29: Unexplained ($)
A30: R1 | B30: GST collected (1A) | C30: Online sales cut-off: GST on S2 attributed to October | D30: =-SUMIF(TB!$A$6:$A$46,2300,TB!$F$6:$F$46) -> 5015000 | E30: =D21 -> 5000700 | F30: =D30-E30 -> 14300 | G30: =-D9*$D$5 -> 14300 | H30: =ROUND(F30-G30,2) -> 0
A31: R2 | B31: GST paid (1B) | C31: GST on petty cash / card purchases not coded in GL (journal on Rec_GST, GST-01) | D31: =SUMIF(TB!$A$6:$A$46,2310,TB!$F$6:$F$46) -> 2350000 | E31: =D22 -> 2358420 | F31: =D31-E31 -> -8420 | G31: =Rec_GST!D22 -> -8420 | H31: =ROUND(F31-G31,2) -> 0
A32: R3 | B32: PAYG withholding (W2) | C32: GL payable agrees to W2 | D32: =-SUMIF(TB!$A$6:$A$46,2100,TB!$F$6:$F$46) -> 1950000 | E32: =D25 -> 1950000 | F32: =D32-E32 -> 0 | G32: 0 | H32: =ROUND(F32-G32,2) -> 0
B33: Total | D33: =SUM(D30:D32) -> 9315000 | E33: =SUM(E30:E32) -> 9309120 | F33: =SUM(F30:F32) -> 5880 | G33: =SUM(G30:G32) -> 5880 | H33: =SUM(H30:H32) -> 0
B35: Analytical review | C35: Basis | D35: Result | E35: Flag
B36: Effective GST rate on taxable sales | C36: 1A / taxable sales; expect the GST rate | D36: =IF(D11=0,0,D21/D11) -> 0.1 | E36: =IF(ABS(D36-$D$5)<0.0005,"OK","Review") -> OK
B37: Input tax credits as % of GST on sales | C37: 1B / 1A | D37: =IF(D21=0,0,D22/D21) -> 0.47161797
B38: PAYG withheld as % of salary and wages | C38: W2 / W1 | D38: =IF(D24=0,0,D25/D24) -> 0.16525424
B39: BAS taxable sales vs P&L net sales | C39: Explained by the cut-off item S2 | D39: =IF(D8=0,0,D11/D8-1) -> -0.0028514457
A41: IAS workings - entity not registered for GST (simulated property holding entity)
A42: Ref | B42: Item | C42: Source / basis | D42: Amount ($)
A43: W1 | B43: Total salary, wages and other payments | C43: Simulated payroll | D43: 185000
A44: W2 | B44: Amount withheld from payments | C44: Simulated | D44: 31450
B45: PAYG instalment income | C45: Simulated rental income for the month | D45: 2400000
B46: PAYG instalment rate | C46: Simulated; in practice the ATO notifies the rate | D46: 0.015
B47: PAYG instalment payable | D47: =ROUND(D45*D46,0) -> 36000
B48: Total payable to ATO (IAS) | D48: =D44+D47 -> 67450
A50: Sign-off
A51: Prepared by | B51: =Inputs!$C$6 -> Bhagyashree Amblimath | D51: 46300
A52: Reviewed by | B52: =Inputs!$C$7 -> Financial Controller (simulated)
A53: Lodged on

Sheet FBT
A1: Fringe Benefits Tax - FBT Year Schedule
A2: FBT year runs 1 April to 31 March. Schedule shows projected full-year benefits with an accrual to period end.
A3: =Inputs!$C$3 -> Specialty retailer (simulated, Adairs-style)
A4: FBT year start | E4: 46113 | F4: Input
A5: FBT year end | E5: =DATE(YEAR(E4)+1,3,31) -> 46477
A6: Days in FBT year | E6: =E5-E4+1 -> 365
A7: Period end | E7: =Inputs!$C$5 -> 46295
A8: Months of FBT year elapsed at period end | E8: =(YEAR(E7)-YEAR(E4))*12+MONTH(E7)-MONTH(E4)+1 -> 6
A9: FBT rate | E9: 0.47 | F9: ATO FBT rates and thresholds: 47% for FBT years ending 31 Mar 2023 to 2027 (checked 9-Oct-2026)
A10: Type 1 gross-up rate (GST credit entitled) | E10: 2.0802 | F10: ATO: 2.0802 for FBT years ending 31 Mar 2023 to 2027
A11: Type 2 gross-up rate (no GST credit) | E11: 1.8868 | F11: ATO: 1.8868 for FBT years ending 31 Mar 2023 to 2027
A12: Car statutory fraction (flat rate) | E12: 0.2 | F12: Statutory formula method, flat 20% regardless of distance
A13: Meal entertainment: 50/50 split method | E13: 0.5 | F13: Taxable value = 50% of actual expenditure
A14: Reportable fringe benefits threshold ($) | E14: 2000 | F14: Grossed-up (Type 2) value above this is reported for the employee; verify threshold each year
A15: FBT return lodgement due | E15: 46528 | F15: Verify against ATO key dates (tax agent lodgement program can differ)
A16: FBT payment due | E16: 46535 | F16: Verify against ATO key dates
A18: Ref | B18: Employee | C18: Benefit | D18: Type | E18: Cost / base value ($) | F18: Days | G18: Basis % | H18: Employee contribution ($) | I18: Taxable value ($) | J18: Gross-up rate | K18: Grossed-up value ($) | L18: FBT payable ($) | M18: Employee-specific (Y/N) | N18: Reportable amount ($) | O18: Report?
A19: FB-01 | B19: Employee A | C19: Car fringe benefit (statutory formula) | D19: 1 | E19: 62000 | F19: 365 | G19: =$E$12 -> 0.2 | H19: 3000 | I19: =IF(E19="","",MAX(0,E19*G19*F19/$E$6-H19)) -> 9400 | J19: =IF(D19="","",IF(D19=1,$E$10,$E$11)) -> 2.0802 | K19: =IF(I19="","",I19*J19) -> 19553.88 | L19: =IF(K19="","",K19*$E$9) -> 9190.3236 | M19: Y | N19: =IF(AND(M19="Y",I19<>""),I19*$E$11,0) -> 17735.92 | O19: =IF(AND(M19="Y",N19>$E$14),"Report","") -> Report
A20: FB-02 | B20: Employee B | C20: Car fringe benefit (statutory formula), part year | D20: 1 | E20: 48500 | F20: 275 | G20: =$E$12 -> 0.2 | H20: 0 | I20: =IF(E20="","",MAX(0,E20*G20*F20/$E$6-H20)) -> 7308.2192 | J20: =IF(D20="","",IF(D20=1,$E$10,$E$11)) -> 2.0802 | K20: =IF(I20="","",I20*J20) -> 15202.558 | L20: =IF(K20="","",K20*$E$9) -> 7145.202 | M20: Y | N20: =IF(AND(M20="Y",I20<>""),I20*$E$11,0) -> 13789.148 | O20: =IF(AND(M20="Y",N20>$E$14),"Report","") -> Report
A21: FB-03 | B21: Employee C | C21: Car fringe benefit (statutory formula) | D21: 1 | E21: 71200 | F21: 365 | G21: =$E$12 -> 0.2 | H21: 4500 | I21: =IF(E21="","",MAX(0,E21*G21*F21/$E$6-H21)) -> 9740 | J21: =IF(D21="","",IF(D21=1,$E$10,$E$11)) -> 2.0802 | K21: =IF(I21="","",I21*J21) -> 20261.148 | L21: =IF(K21="","",K21*$E$9) -> 9522.7396 | M21: Y | N21: =IF(AND(M21="Y",I21<>""),I21*$E$11,0) -> 18377.432 | O21: =IF(AND(M21="Y",N21>$E$14),"Report","") -> Report
A22: FB-04 | B22: Employee D | C22: Expense payment benefit: wellbeing reimbursements | D22: 1 | E22: 6400 | F22: =$E$6 -> 365 | G22: 1 | H22: 0 | I22: =IF(E22="","",MAX(0,E22*G22*F22/$E$6-H22)) -> 6400 | J22: =IF(D22="","",IF(D22=1,$E$10,$E$11)) -> 2.0802 | K22: =IF(I22="","",I22*J22) -> 13313.28 | L22: =IF(K22="","",K22*$E$9) -> 6257.2416 | M22: Y | N22: =IF(AND(M22="Y",I22<>""),I22*$E$11,0) -> 12075.52 | O22: =IF(AND(M22="Y",N22>$E$14),"Report","") -> Report
A23: FB-05 | B23: Various | C23: Meal entertainment (50/50 split method) | D23: 2 | E23: 38000 | F23: =$E$6 -> 365 | G23: =$E$13 -> 0.5 | H23: 0 | I23: =IF(E23="","",MAX(0,E23*G23*F23/$E$6-H23)) -> 19000 | J23: =IF(D23="","",IF(D23=1,$E$10,$E$11)) -> 1.8868 | K23: =IF(I23="","",I23*J23) -> 35849.2 | L23: =IF(K23="","",K23*$E$9) -> 16849.124 | M23: N | N23: =IF(AND(M23="Y",I23<>""),I23*$E$11,0) -> 0 | O23: =IF(AND(M23="Y",N23>$E$14),"Report","")
A24: FB-06 | B24: Various | C24: Other expense payment benefits (no GST credit) | D24: 2 | E24: 2800 | F24: =$E$6 -> 365 | G24: 1 | H24: 0 | I24: =IF(E24="","",MAX(0,E24*G24*F24/$E$6-H24)) -> 2800 | J24: =IF(D24="","",IF(D24=1,$E$10,$E$11)) -> 1.8868 | K24: =IF(I24="","",I24*J24) -> 5283.04 | L24: =IF(K24="","",K24*$E$9) -> 2483.0288 | M24: N | N24: =IF(AND(M24="Y",I24<>""),I24*$E$11,0) -> 0 | O24: =IF(AND(M24="Y",N24>$E$14),"Report","")
I25: =IF(E25="","",MAX(0,E25*G25*F25/$E$6-H25)) | J25: =IF(D25="","",IF(D25=1,$E$10,$E$11)) | K25: =IF(I25="","",I25*J25) | L25: =IF(K25="","",K25*$E$9) | N25: =IF(AND(M25="Y",I25<>""),I25*$E$11,0) -> 0 | O25: =IF(AND(M25="Y",N25>$E$14),"Report","")
I26: =IF(E26="","",MAX(0,E26*G26*F26/$E$6-H26)) | J26: =IF(D26="","",IF(D26=1,$E$10,$E$11)) | K26: =IF(I26="","",I26*J26) | L26: =IF(K26="","",K26*$E$9) | N26: =IF(AND(M26="Y",I26<>""),I26*$E$11,0) -> 0 | O26: =IF(AND(M26="Y",N26>$E$14),"Report","")
I27: =IF(E27="","",MAX(0,E27*G27*F27/$E$6-H27)) | J27: =IF(D27="","",IF(D27=1,$E$10,$E$11)) | K27: =IF(I27="","",I27*J27) | L27: =IF(K27="","",K27*$E$9) | N27: =IF(AND(M27="Y",I27<>""),I27*$E$11,0) -> 0 | O27: =IF(AND(M27="Y",N27>$E$14),"Report","")
I28: =IF(E28="","",MAX(0,E28*G28*F28/$E$6-H28)) | J28: =IF(D28="","",IF(D28=1,$E$10,$E$11)) | K28: =IF(I28="","",I28*J28) | L28: =IF(K28="","",K28*$E$9) | N28: =IF(AND(M28="Y",I28<>""),I28*$E$11,0) -> 0 | O28: =IF(AND(M28="Y",N28>$E$14),"Report","")
C29: Total | I29: =SUM(I19:I28) -> 54648.219 | K29: =SUM(K19:K28) -> 109463.11 | L29: =SUM(L19:L28) -> 51447.66 | N29: =SUM(N19:N28) -> 61978.02
A31: FBT summary
A32: Type 1 taxable value | E32: =SUMIF($D$19:$D$28,1,$I$19:$I$28) -> 32848.219
A33: Type 1 grossed-up value | E33: =E32*$E$10 -> 68330.866
A34: Type 2 taxable value | E34: =SUMIF($D$19:$D$28,2,$I$19:$I$28) -> 21800
A35: Type 2 grossed-up value | E35: =E34*$E$11 -> 41132.24
A36: Total grossed-up value | E36: =E33+E35 -> 109463.11
A37: FBT payable: projected full FBT year | E37: =E36*$E$9 -> 51447.66
A38: Check: summary agrees to schedule total (difference) | E38: =ROUND(E37-L29,2) -> 0 | F38: =IF(E38=0,"OK","Review") -> OK
A39: FBT accrued to period end (months elapsed / 12) | E39: =E37*$E$8/12 -> 25723.83
A40: Less: FBT accrued in GL at period end | E40: 0 | F40: No FBT accrual account exists in the simulated TB
A41: Proposed accrual journal (not posted): Dr FBT expense / Cr FBT payable | E41: =E39-E40 -> 25723.83
A42: Employees with reportable fringe benefits amounts | E42: =COUNTIF($O$19:$O$28,"Report") -> 4
A44: Notes and judgements
A45: 1. Type 1 vs Type 2 depends on whether a GST credit was claimed on the benefit: keep the tax invoice and credit evidence on file.
A46: 2. Gross-up first, then apply the 47% rate. Applying the rate to the raw taxable value understates FBT.
A47: 3. Reportable fringe benefits amounts use the Type 2 gross-up rate even for Type 1 benefits.
A48: 4. Exempt benefits (for example eligible electric cars and minor benefits) are excluded here: document the exemption basis for each before omitting.
A49: 5. Employee contributions must be after-tax and supported by declarations. Cars use the statutory formula method; operating cost method not modelled.
A50: 6. Posting the proposed accrual needs new FBT payable and expense accounts in the chart; it is not in the simulated TB so the close controls are unaffected.
A52: Sign-off
A53: Prepared by | C53: =Inputs!$C$6 -> Bhagyashree Amblimath | E53: 46300
A54: Reviewed by | C54: =Inputs!$C$7 -> Financial Controller (simulated)

Sheet Payroll
A1: Payroll Oversight
A2: =Inputs!$C$3 -> Specialty retailer (simulated, Adairs-style)
A3: Period end | B3: =Inputs!$C$5 -> 46295
A4: Status: built. Payroll register figures and parameters are simulated inputs (blue); everything else links to TB, BAS_IAS and Rec_Payroll.
A6: 1. Payroll parameters
A7: Parameter | B7: Value | C7: Basis / source
A8: Super guarantee rate (on qualifying earnings) | B8: 0.12 | C8: ATO: 12% of qualifying earnings; Payday Super applies from 1 July 2026 (checked 9-Oct-2026)
A9: Qualifying earnings as share of gross wages | B9: 1 | C9: Simplified: all gross wages treated as qualifying earnings
A10: PAYG effective withholding rate: lower bound | B10: 0.14 | C10: Simulated analytical range for a mixed full-time / part-time / casual retail workforce
A11: PAYG effective withholding rate: upper bound | B11: 0.2 | C11: Simulated analytical range
A12: Payday Super window: max calendar days of super expense unpaid at period end | B12: 10 | C12: 7 business days after payday is roughly 9-10 calendar days
A13: Reconciliation tolerance ($) | B13: =Inputs!$C$12 -> 1 | C13: From Inputs tab
A14: Average FTE: stores | B14: 1350 | C14: Simulated headcount
A15: Average FTE: head office | B15: 280 | C15: Simulated headcount
A17: 2. Payroll register to GL journal (September pay periods)
A18: Journal line | B18: GL a/c | C18: Debit ($) | D18: Credit ($) | E18: Per GL month movement ($) | F18: Difference ($) | G18: Status | H18: Note
A19: Gross wages: stores | B19: 6000 | C19: 8900000 | E19: =SUMIF(TB!$A$6:$A$46,$B19,TB!$G$6:$G$46) -> 8900000 | F19: =C19-E19 -> 0 | G19: =IF(ABS(F19)<=$B$13,"OK","INVESTIGATE") -> OK | H19: Register gross by cost centre (simulated)
A20: Gross wages: head office | B20: 6010 | C20: 3100000 | E20: =SUMIF(TB!$A$6:$A$46,$B20,TB!$G$6:$G$46) -> 3100000 | F20: =C20-E20 -> 0 | G20: =IF(ABS(F20)<=$B$13,"OK","INVESTIGATE") -> OK
A21: Superannuation expense (qualifying earnings x SG rate) | B21: 6020 | C21: =ROUND((C19+C20)*$B$9*$B$8,0) -> 1440000 | E21: =SUMIF(TB!$A$6:$A$46,$B21,TB!$G$6:$G$46) -> 1440000 | F21: =C21-E21 -> 0 | G21: =IF(ABS(F21)<=$B$13,"OK","INVESTIGATE") -> OK | H21: Calculated, then compared to GL; a difference means a rate or base error
A22: PAYG withholding payable | B22: 2100 | D22: 1950000 | H22: Withheld per register (simulated); liability roll in section 5
A23: Superannuation payable | B23: 2110 | D23: =C21 -> 1440000
A24: Net pay to bank / payroll clearing | B24: 1000 | D24: =C19+C20-D22 -> 10050000 | H24: Gross wages less PAYG withheld; no other deductions assumed
A25: Total | C25: =SUM(C19:C24) -> 13440000 | D25: =SUM(D19:D24) -> 13440000 | G25: =IF(ROUND(C25-D25,0)=0,"BALANCED","OUT OF BALANCE") -> BALANCED
A27: 3. PAYG withholding and BAS tie-out
A28: Check | B28: Per payroll register ($) | C28: Per BAS / GL ($) | D28: Difference ($) | E28: Status
A29: W1: salary and wages (gross less non-cash increase in accrued wages and leave) | B29: =C19+C20+SUMIF(TB!$A$6:$A$46,2120,TB!$G$6:$G$46)+SUMIF(TB!$A$6:$A$46,2130,TB!$G$6:$G$46) -> 11800000 | C29: =BAS_IAS!$D$24 -> 11800000 | D29: =B29-C29 -> 0 | E29: =IF(ABS(D29)<=$B$13,"OK","INVESTIGATE") -> OK
A30: W2: amount withheld from payments | B30: =D22 -> 1950000 | C30: =BAS_IAS!$D$25 -> 1950000 | D30: =B30-C30 -> 0 | E30: =IF(ABS(D30)<=$B$13,"OK","INVESTIGATE") -> OK
A31: Effective PAYG rate: withheld / gross wages (expected range in section 1) | B31: =IF(C19+C20=0,0,D22/(C19+C20)) -> 0.1625 | E31: =IF(AND(B31>=$B$10,B31<=$B$11),"IN RANGE","REVIEW") -> IN RANGE
A33: 4. Superannuation guarantee check (Payday Super)
A34: Check | B34: Value | C34: Status
A35: Qualifying earnings (gross wages x qualifying share) | B35: =(C19+C20)*$B$9 -> 12000000
A36: Expected super guarantee (qualifying earnings x SG rate) | B36: =ROUND(B35*$B$8,0) -> 1440000
A37: Super expense per GL (6020 month movement) | B37: =E21 -> 1440000
A38: Difference | B38: =B36-B37 -> 0 | C38: =IF(ABS(B38)<=$B$13,"OK","INVESTIGATE") -> OK
A39: Super payable per GL (2110, liability shown positive) | B39: =-SUMIF(TB!$A$6:$A$46,2110,TB!$F$6:$F$46) -> 345000
A40: Super payable as calendar days of super expense | B40: =IF(B37=0,0,B39/(B37/DAY(Inputs!$C$5))) -> 7.1875 | C40: =IF(B40<=$B$12,"WITHIN WINDOW","REVIEW: LATE-PAYMENT RISK") -> WITHIN WINDOW | D40: Payday Super: contributions must reach the fund within 7 business days of payday
A41: Super payments made but not yet journalised (Rec_Payroll PAY-01) | B41: =Rec_Payroll!$D$22 -> -96000 | D41: Journal pending: Dr 2110 / Cr 1000. Super payable per GL is overstated until posted.
A43: 5. Payroll liabilities: GL to payroll system report
A44: Account | B44: Per GL ($) | C44: Per payroll system ($) | D44: Difference ($) | E44: Explained: GL adjustment ($) | F44: Explained: timing ($) | G44: Unexplained ($) | H44: Reference
A45: 2100 PAYG withholding payable | B45: =-SUMIF(TB!$A$6:$A$46,2100,TB!$F$6:$F$46) -> 1950000 | C45: 1950000 | D45: =B45-C45 -> 0 | E45: 0 | F45: 0 | G45: =D45-E45-F45 -> 0 | H45: Agrees
A46: 2110 Superannuation payable | B46: =-SUMIF(TB!$A$6:$A$46,2110,TB!$F$6:$F$46) -> 345000 | C46: 249000 | D46: =B46-C46 -> 96000 | E46: =-Rec_Payroll!$D$22 -> 96000 | F46: 0 | G46: =D46-E46-F46 -> 0 | H46: PAY-01: super paid 29-Sep (SuperStream) not journalised
A47: 2120 Accrued wages | B47: =-SUMIF(TB!$A$6:$A$46,2120,TB!$F$6:$F$46) -> 2300000 | C47: 2255000 | D47: =B47-C47 -> 45000 | E47: 0 | F47: =Rec_Payroll!$D$23 -> 45000 | G47: =D47-E47-F47 -> 0 | H47: PAY-02: termination payout calculated 30-Sep, paid 2-Oct
A48: Total | B48: =SUM(B45:B47) -> 4595000 | C48: =SUM(C45:C47) -> 4454000 | D48: =SUM(D45:D47) -> 141000 | E48: =SUM(E45:E47) -> 96000 | F48: =SUM(F45:F47) -> 45000 | G48: =SUM(G45:G47) -> 0
A49: Check: payroll system total agrees to Rec_Payroll source balance | B49: =C48 -> 4454000 | C49: =Rec_Payroll!$D$14 -> 4454000 | D49: =B49-C49 -> 0 | E49: =IF(ABS(D49)<=$B$13,"OK","INVESTIGATE") -> OK
A50: Check: unexplained difference across accounts | B50: =G48 -> 0 | E50: =IF(ABS(B50)<=$B$13,"OK","INVESTIGATE") -> OK
A52: 6. Annual leave provision movement and on-cost review
A53: Item | B53: Value ($) | C53: Basis
A54: Opening provision (2130, prior month TB) | B54: =-SUMIF(TB!$A$6:$A$46,2130,TB!$E$6:$E$46) -> 5050000
A55: Add: leave accrued in month | B55: 620000 | C55: Payroll leave report (simulated)
A56: Less: leave taken and paid out | B56: -570000 | C56: Payroll leave report (simulated)
A57: Expected closing provision | B57: =SUM(B54:B56) -> 5100000
A58: Closing provision per TB (2130) | B58: =-SUMIF(TB!$A$6:$A$46,2130,TB!$F$6:$F$46) -> 5100000
A59: Difference | B59: =B57-B58 -> 0 | C59: =IF(ABS(B59)<=$B$13,"OK","INVESTIGATE") -> OK
A60: Super on-cost on leave accrued (accrual x SG rate) | B60: =ROUND(B55*$B$8,0) -> 74400 | C60: Confirm the accrual is on-cost loaded. Payroll tax and workers compensation loadings not modelled.
A61: Provision as days of gross payroll | B61: =IF(C19+C20=0,0,B58/((C19+C20)/DAY(Inputs!$C$5))) -> 12.75
A62: Provision as % of annualised gross wages | B62: =IF(C19+C20=0,0,B58/((C19+C20)*12)) -> 0.035416667 | C62: Trend indicator: a rising ratio means leave is accruing faster than it is taken
A64: 7. Payroll analytics
A65: Metric | B65: Stores | C65: Head office | D65: Total
A66: Gross wages per FTE per month ($) | B66: =IF($B$14=0,0,C19/$B$14) -> 6592.5926 | C66: =IF($B$15=0,0,C20/$B$15) -> 11071.429 | D66: =IF($B$14+$B$15=0,0,(C19+C20)/($B$14+$B$15)) -> 7361.9632
A67: Share of gross wages | B67: =IF(C19+C20=0,0,C19/(C19+C20)) -> 0.74166667 | C67: =IF(C19+C20=0,0,C20/(C19+C20)) -> 0.25833333 | D67: =B67+C67 -> 1
A68: Store wages as % of net sales | B68: =IF(Variance!$C$9=0,0,C19/Variance!$C$9) -> 0.1774676
A69: Store wages: variance to budget ($, favourable / (unfavourable)) | B69: =Variance!$E$16 -> -200000
A71: Payroll check summary
A72: Check | B72: Result
A73: Register expense lines agree to GL | B73: =IF(SUMPRODUCT(--(ABS(F19:F21)>$B$13))=0,"PASS","FAIL") -> PASS
A74: Payroll journal balances | B74: =IF(ROUND(C25-D25,0)=0,"PASS","FAIL") -> PASS
A75: W1 and W2 agree to BAS | B75: =IF(AND(ABS(D29)<=$B$13,ABS(D30)<=$B$13),"PASS","FAIL") -> PASS
A76: Effective PAYG rate within expected range | B76: =IF(E31="IN RANGE","PASS","REVIEW") -> PASS
A77: Super guarantee calculation agrees to GL | B77: =IF(ABS(B38)<=$B$13,"PASS","FAIL") -> PASS
A78: Super payable within Payday Super window | B78: =IF(B40<=$B$12,"PASS","REVIEW") -> PASS
A79: Payroll liabilities: no unexplained differences | B79: =IF(AND(ABS(B50)<=$B$13,ABS(D49)<=$B$13),"PASS","FAIL") -> PASS
A80: Leave provision roll-forward agrees to GL | B80: =IF(ABS(B59)<=$B$13,"PASS","FAIL") -> PASS
A81: Overall payroll status | B81: =IF(COUNTIF(B73:B80,"FAIL")>0,"FAIL",IF(COUNTIF(B73:B80,"REVIEW")>0,"REVIEW","ALL PASS")) -> ALL PASS
A82: Journals pending from Rec_Payroll ($, GL adjustments to post) | B82: =Rec_Payroll!$D$11 -> -96000
A84: Sign-off
A85: Prepared by | B85: =Inputs!$C$6 -> Bhagyashree Amblimath | D85: 46300
A86: Reviewed by | B86: =Inputs!$C$7 -> Financial Controller (simulated) | E86: <- reviewer to date on sign-off

Sheet Forecast
A1: Rolling Forecast and Budget Model
A2: =Inputs!$C$3 -> Specialty retailer (simulated, Adairs-style)
A3: Period end | B3: =Inputs!$C$5 -> 46295
A4: Status: built. 12-month rolling forecast from the Sep-26 close. Drivers, seasonality and scenario levers are simulated inputs (blue).
A5: Scenario selected | B5: Base | C5: <- choose Base or Downside; the whole model recalculates
A7: A. Scenario levers
A8: Lever | B8: Base | C8: Downside | D8: Selected
A9: Traffic and online sessions vs seasonal baseline (% change) | B9: 0 | C9: -0.04 | D9: =IF($B$5="Base",B9,C9) -> 0 | E9: Simulated levers. Replace with management assumptions.
A10: Conversion rate (relative % change) | B10: 0 | C10: -0.03 | D10: =IF($B$5="Base",B10,C10) -> 0
A11: Basket size / AOV (% change vs Sep-26) | B11: 0.01 | C11: -0.015 | D11: =IF($B$5="Base",B11,C11) -> 0.01
A12: COGS % of net sales (change, percentage points) | B12: 0 | C12: 0.01 | D12: =IF($B$5="Base",B12,C12) -> 0
A13: Shrinkage % of net sales (change, percentage points) | B13: 0 | C13: 0.002 | D13: =IF($B$5="Base",B13,C13) -> 0
A14: Fixed cost inflation per month | B14: 0.0025 | C14: 0.004 | D14: =IF($B$5="Base",B14,C14) -> 0.0025
A15: Underlying monthly traffic growth | B15: 0.003 | C15: 0 | D15: =IF($B$5="Base",B15,C15) -> 0.003
A16: Depreciation growth per month (capex roll-in) | B16: 0.005 | C16: 0.005 | D16: =IF($B$5="Base",B16,C16) -> 0.005
A18: B. Sep-26 calibration (drivers back-solved from closed actuals)
A19: Driver | B19: Stores | C19: Online | D19: Basis
A20: Traffic (store visits) / online sessions | B20: 2550000 | C20: 4100000 | D20: Simulated; replace with footfall counter / web analytics
A21: Conversion rate | B21: 0.15 | C21: 0.022 | D21: Simulated
A22: Transactions / orders | B22: =B20*B21 -> 382500 | C22: =C20*C21 -> 90200
A23: Basket size / AOV ($, ex GST) | B23: =IF(B22=0,0,Variance!$C$6/B22) -> 99.869281 | C23: =IF(C22=0,0,Variance!$C$7/C22) -> 154.102 | D23: Sales per Variance tab divided by transactions
A24: Returns and discounts % of gross sales | B24: =IF(Variance!$C$6+Variance!$C$7=0,0,-Variance!$C$8/(Variance!$C$6+Variance!$C$7)) -> 0.037428023
A25: COGS % of net sales | B25: =IF(Variance!$C$9=0,0,Variance!$C$10/Variance!$C$9) -> 0.39082752
A26: Freight inwards % of net sales | B26: =IF(Variance!$C$9=0,0,Variance!$C$11/Variance!$C$9) -> 0.033898305
A27: Shrinkage and provisions % of net sales | B27: =IF(Variance!$C$9=0,0,Variance!$C$12/Variance!$C$9) -> 0.0083748754
A28: Store wages % of net sales | B28: =IF(Variance!$C$9=0,0,Variance!$C$16/Variance!$C$9) -> 0.1774676
A29: Marketing % of net sales | B29: =IF(Variance!$C$9=0,0,Variance!$C$20/Variance!$C$9) -> 0.066799601
A30: Bank and merchant fees % of net sales | B30: =IF(Variance!$C$9=0,0,Variance!$C$23/Variance!$C$9) -> 0.013758724
A31: Superannuation rate on wages (from Payroll tab) | B31: =Payroll!$B$8 -> 0.12
A32: Variable share of operating expenses (budget proxy) | B32: =IF(Variance!$D$25=0,0,(Variance!$D$16*(1+B31)+Variance!$D$20+Variance!$D$23)/Variance!$D$25) -> 0.57658201 | D32: Derived from Sep-26 budget: store wages (with super), marketing and merchant fees flex with sales
A34: C. Monthly forecast ($)
A35: Rolling forecast | B35: =Inputs!$C$5 -> 46295 | C35: =EOMONTH(Inputs!$C$5,C36) -> 46326 | D35: =EOMONTH(Inputs!$C$5,D36) -> 46356 | E35: =EOMONTH(Inputs!$C$5,E36) -> 46387 | F35: =EOMONTH(Inputs!$C$5,F36) -> 46418 | G35: =EOMONTH(Inputs!$C$5,G36) -> 46446 | H35: =EOMONTH(Inputs!$C$5,H36) -> 46477 | I35: =EOMONTH(Inputs!$C$5,I36) -> 46507 | J35: =EOMONTH(Inputs!$C$5,J36) -> 46538 | ... N35: =EOMONTH(Inputs!$C$5,N36) -> 46660 | O35: 12 months
A36: Month index (0 = last closed month, actual) | B36: 0 | C36: =B36+1 -> 1 | D36: =C36+1 -> 2 | E36: =D36+1 -> 3 | F36: =E36+1 -> 4 | G36: =F36+1 -> 5 | H36: =G36+1 -> 6 | I36: =H36+1 -> 7 | J36: =I36+1 -> 8 | ... N36: =M36+1 -> 12
A37: Seasonality index (Sep-26 = 1.00) | B37: 1 | C37: 1.03 | D37: 1.28 | E37: 1.4 | F37: 0.92 | G37: 0.86 | H37: 0.95 | I37: 0.93 | J37: 0.97 | K37: 1.06 | L37: 0.98 | M37: 0.96 | N37: 1
A38: Simulated seasonality: Black Friday / Christmas peak, EOFY sale in June. Replace with 3 years of actual monthly sales indices.
A39: Stores
A40: Traffic (visits) | B40: =$B$20 -> 2550000 | C40: =$B$20*C$37*(1+$D$15)^C$36*(1+$D$9) -> 2634379.5 | D40: =$B$20*D$37*(1+$D$15)^D$36*(1+$D$9) -> 3283613.4 | E40: =$B$20*E$37*(1+$D$15)^E$36*(1+$D$9) -> 3602226.5 | F40: =$B$20*F$37*(1+$D$15)^F$36*(1+$D$9) -> 2374278.9 | G40: =$B$20*G$37*(1+$D$15)^G$36*(1+$D$9) -> 2226093 | H40: =$B$20*H$37*(1+$D$15)^H$36*(1+$D$9) -> 2466433.3 | I40: =$B$20*I$37*(1+$D$15)^I$36*(1+$D$9) -> 2421752 | J40: =$B$20*J$37*(1+$D$15)^J$36*(1+$D$9) -> 2533491.1 | ... N40: =$B$20*N$37*(1+$D$15)^N$36*(1+$D$9) -> 2643329.9 | O40: =SUM(C40:N40) -> 32067457
A41: Conversion rate | B41: =$B$21 -> 0.15 | C41: =$B$21*(1+$D$10) -> 0.15 | D41: =$B$21*(1+$D$10) -> 0.15 | E41: =$B$21*(1+$D$10) -> 0.15 | F41: =$B$21*(1+$D$10) -> 0.15 | G41: =$B$21*(1+$D$10) -> 0.15 | H41: =$B$21*(1+$D$10) -> 0.15 | I41: =$B$21*(1+$D$10) -> 0.15 | J41: =$B$21*(1+$D$10) -> 0.15 | ... N41: =$B$21*(1+$D$10) -> 0.15
A42: Transactions | B42: =B40*B41 -> 382500 | C42: =C40*C41 -> 395156.92 | D42: =D40*D41 -> 492542.01 | E42: =E40*E41 -> 540333.97 | F42: =F40*F41 -> 356141.84 | G42: =G40*G41 -> 333913.94 | H42: =H40*H41 -> 369965 | I42: =I40*I41 -> 363262.79 | ... N42: =N40*N41 -> 396499.49 | O42: =SUM(C42:N42) -> 4810118.6
A43: Basket size ($) | B43: =$B$23 -> 99.869281 | C43: =$B$23*(1+$D$11) -> 100.86797 | D43: =$B$23*(1+$D$11) -> 100.86797 | E43: =$B$23*(1+$D$11) -> 100.86797 | F43: =$B$23*(1+$D$11) -> 100.86797 | G43: =$B$23*(1+$D$11) -> 100.86797 | H43: =$B$23*(1+$D$11) -> 100.86797 | I43: =$B$23*(1+$D$11) -> 100.86797 | J43: =$B$23*(1+$D$11) -> 100.86797 | ... N43: =$B$23*(1+$D$11) -> 100.86797
A44: Sales: stores | B44: =B42*B43 -> 38200000 | C44: =C42*C43 -> 39858678 | D44: =D42*D43 -> 49681714 | E44: =E42*E43 -> 54502393 | F44: =F42*F43 -> 35923306 | G44: =G42*G43 -> 33681223 | H44: =H42*H43 -> 37317620 | I44: =I42*I43 -> 36641582 | ... N44: =N42*N43 -> 39994100 | O44: =SUM(C44:N44) -> 4.8518692e+08
A45: Online
A46: Sessions | B46: =$C$20 -> 4100000 | C46: =$C$20*C$37*(1+$D$15)^C$36*(1+$D$9) -> 4235669 | D46: =$C$20*D$37*(1+$D$15)^D$36*(1+$D$9) -> 5279535.2 | E46: =$C$20*E$37*(1+$D$15)^E$36*(1+$D$9) -> 5791815.1 | F46: =$C$20*F$37*(1+$D$15)^F$36*(1+$D$9) -> 3817468.1 | G46: =$C$20*G$37*(1+$D$15)^G$36*(1+$D$9) -> 3579208.3 | H46: =$C$20*H$37*(1+$D$15)^H$36*(1+$D$9) -> 3965637.9 | I46: =$C$20*I$37*(1+$D$15)^I$36*(1+$D$9) -> 3893797.3 | J46: =$C$20*J$37*(1+$D$15)^J$36*(1+$D$9) -> 4073456.2 | ... N46: =$C$20*N$37*(1+$D$15)^N$36*(1+$D$9) -> 4250059.9 | O46: =SUM(C46:N46) -> 51559441
A47: Conversion rate | B47: =$C$21 -> 0.022 | C47: =$C$21*(1+$D$10) -> 0.022 | D47: =$C$21*(1+$D$10) -> 0.022 | E47: =$C$21*(1+$D$10) -> 0.022 | F47: =$C$21*(1+$D$10) -> 0.022 | G47: =$C$21*(1+$D$10) -> 0.022 | H47: =$C$21*(1+$D$10) -> 0.022 | I47: =$C$21*(1+$D$10) -> 0.022 | J47: =$C$21*(1+$D$10) -> 0.022 | ... N47: =$C$21*(1+$D$10) -> 0.022
A48: Orders | B48: =B46*B47 -> 90200 | C48: =C46*C47 -> 93184.718 | D48: =D46*D47 -> 116149.78 | E48: =E46*E47 -> 127419.93 | F48: =F46*F47 -> 83984.298 | G48: =G46*G47 -> 78742.582 | H48: =H46*H47 -> 87244.035 | I48: =I46*I47 -> 85663.54 | ... N48: =N46*N47 -> 93501.318 | O48: =SUM(C48:N48) -> 1134307.7
A49: AOV ($) | B49: =$C$23 -> 154.102 | C49: =$C$23*(1+$D$11) -> 155.64302 | D49: =$C$23*(1+$D$11) -> 155.64302 | E49: =$C$23*(1+$D$11) -> 155.64302 | F49: =$C$23*(1+$D$11) -> 155.64302 | G49: =$C$23*(1+$D$11) -> 155.64302 | H49: =$C$23*(1+$D$11) -> 155.64302 | I49: =$C$23*(1+$D$11) -> 155.64302 | J49: =$C$23*(1+$D$11) -> 155.64302 | ... N49: =$C$23*(1+$D$11) -> 155.64302
A50: Sales: online | B50: =B48*B49 -> 13900000 | C50: =C48*C49 -> 14503551 | D50: =D48*D49 -> 18077901 | E50: =E48*E49 -> 19832023 | F50: =F48*F49 -> 13071569 | G50: =G48*G49 -> 12255733 | H50: =H48*H49 -> 13578925 | I50: =I48*I49 -> 13332932 | ... N50: =N48*N49 -> 14552827 | O50: =SUM(C50:N50) -> 1.7654707e+08
A52: Income statement
A53: Sales: stores | B53: =B44 -> 38200000 | C53: =C44 -> 39858678 | D53: =D44 -> 49681714 | E53: =E44 -> 54502393 | F53: =F44 -> 35923306 | G53: =G44 -> 33681223 | H53: =H44 -> 37317620 | I53: =I44 -> 36641582 | ... N53: =N44 -> 39994100 | O53: =SUM(C53:N53) -> 4.8518692e+08
A54: Sales: online | B54: =B50 -> 13900000 | C54: =C50 -> 14503551 | D54: =D50 -> 18077901 | E54: =E50 -> 19832023 | F54: =F50 -> 13071569 | G54: =G50 -> 12255733 | H54: =H50 -> 13578925 | I54: =I50 -> 13332932 | ... N54: =N50 -> 14552827 | O54: =SUM(C54:N54) -> 1.7654707e+08
A55: Sales returns and discounts | B55: =Variance!$C$8 -> -1950000 | C55: =-(C53+C54)*$B$24 -> -2034670.8 | D55: =-(D53+D54)*$B$24 -> -2536108.4 | E55: =-(E53+E54)*$B$24 -> -2782190.2 | F55: =-(F53+F54)*$B$24 -> -1833781.3 | G55: =-(G53+G54)*$B$24 -> -1719329.4 | H55: =-(H53+H54)*$B$24 -> -1904957.1 | I55: =-(I53+I54)*$B$24 -> -1870447.3 | J55: =-(J53+J54)*$B$24 -> -1956749.3 | ... N55: =-(N53+N54)*$B$24 -> -2041583.7 | O55: =SUM(C55:N55) -> -24767395
A56: Net sales | B56: =SUM(B53:B55) -> 50150000 | C56: =SUM(C53:C55) -> 52327558 | D56: =SUM(D53:D55) -> 65223507 | E56: =SUM(E53:E55) -> 71552225 | F56: =SUM(F53:F55) -> 47161094 | G56: =SUM(G53:G55) -> 44217627 | H56: =SUM(H53:H55) -> 48991588 | I56: =SUM(I53:I55) -> 48104066 | ... N56: =SUM(N53:N55) -> 52505344 | O56: =SUM(C56:N56) -> 6.369666e+08
A57: Cost of goods sold | B57: =Variance!$C$10 -> 19600000 | C57: =C56*($B$25+$D$12) -> 20451050 | D57: =D56*($B$25+$D$12) -> 25491141 | E57: =E56*($B$25+$D$12) -> 27964579 | F57: =F56*($B$25+$D$12) -> 18431853 | G57: =G56*($B$25+$D$12) -> 17281465 | H57: =H56*($B$25+$D$12) -> 19147261 | I57: =I56*($B$25+$D$12) -> 18800393 | J57: =J56*($B$25+$D$12) -> 19667839 | ... N57: =N56*($B$25+$D$12) -> 20520533 | O57: =SUM(C57:N57) -> 2.4894407e+08
A58: Freight inwards | B58: =Variance!$C$11 -> 1700000 | C58: =C56*$B$26 -> 1773815.5 | D58: =D56*$B$26 -> 2210966.3 | E58: =E56*$B$26 -> 2425499.2 | F58: =F56*$B$26 -> 1598681.2 | G58: =G56*$B$26 -> 1498902.6 | H58: =H56*$B$26 -> 1660731.8 | I58: =I56*$B$26 -> 1630646.3 | J58: =J56*$B$26 -> 1705884 | ... N58: =N56*$B$26 -> 1779842.2 | O58: =SUM(C58:N58) -> 21592088
A59: Inventory shrinkage and provisions | B59: =Variance!$C$12 -> 420000 | C59: =C56*($B$27+$D$13) -> 438236.78 | D59: =D56*($B$27+$D$13) -> 546238.74 | E59: =E56*($B$27+$D$13) -> 599240.97 | F59: =F56*($B$27+$D$13) -> 394968.28 | G59: =G56*($B$27+$D$13) -> 370317.11 | H59: =H56*($B$27+$D$13) -> 410298.44 | I59: =I56*($B$27+$D$13) -> 402865.56 | J59: =J56*($B$27+$D$13) -> 421453.69 | ... N59: =N56*($B$27+$D$13) -> 439725.71 | O59: =SUM(C59:N59) -> 5334515.9
A60: Total cost of goods sold | B60: =SUM(B57:B59) -> 21720000 | C60: =SUM(C57:C59) -> 22663102 | D60: =SUM(D57:D59) -> 28248346 | E60: =SUM(E57:E59) -> 30989319 | F60: =SUM(F57:F59) -> 20425503 | G60: =SUM(G57:G59) -> 19150685 | H60: =SUM(H57:H59) -> 21218291 | I60: =SUM(I57:I59) -> 20833905 | ... N60: =SUM(N57:N59) -> 22740101 | O60: =SUM(C60:N60) -> 2.7587068e+08
A61: Gross profit | B61: =B56-B60 -> 28430000 | C61: =C56-C60 -> 29664456 | D61: =D56-D60 -> 36975161 | E61: =E56-E60 -> 40562907 | F61: =F56-F60 -> 26735591 | G61: =G56-G60 -> 25066942 | H61: =H56-H60 -> 27773297 | I61: =I56-I60 -> 27270162 | ... N61: =N56-N60 -> 29765243 | O61: =SUM(C61:N61) -> 3.6109592e+08
A62: Gross margin % | B62: =IF(B56=0,0,B61/B56) -> 0.5668993 | C62: =IF(C56=0,0,C61/C56) -> 0.5668993 | D62: =IF(D56=0,0,D61/D56) -> 0.5668993 | E62: =IF(E56=0,0,E61/E56) -> 0.5668993 | F62: =IF(F56=0,0,F61/F56) -> 0.5668993 | G62: =IF(G56=0,0,G61/G56) -> 0.5668993 | H62: =IF(H56=0,0,H61/H56) -> 0.5668993 | I62: =IF(I56=0,0,I61/I56) -> 0.5668993 | ... O62: =IF(O56=0,0,O61/O56) -> 0.5668993
A63: Wages and salaries: stores | B63: =Variance!$C$16 -> 8900000 | C63: =C56*$B$28 -> 9286446 | D63: =D56*$B$28 -> 11575059 | E63: =E56*$B$28 -> 12698202 | F63: =F56*$B$28 -> 8369566 | G63: =G56*$B$28 -> 7847195.9 | H63: =H56*$B$28 -> 8694419.4 | I63: =I56*$B$28 -> 8536913.1 | J63: =J56*$B$28 -> 8930804.4 | ... N63: =N56*$B$28 -> 9317997.2 | O63: =SUM(C63:N63) -> 1.1304093e+08
A64: Wages and salaries: head office | B64: =Variance!$C$17 -> 3100000 | C64: =B64*(1+$D$14) -> 3107750 | D64: =C64*(1+$D$14) -> 3115519.4 | E64: =D64*(1+$D$14) -> 3123308.2 | F64: =E64*(1+$D$14) -> 3131116.4 | G64: =F64*(1+$D$14) -> 3138944.2 | H64: =G64*(1+$D$14) -> 3146791.6 | I64: =H64*(1+$D$14) -> 3154658.6 | J64: =I64*(1+$D$14) -> 3162545.2 | ... N64: =M64*(1+$D$14) -> 3194289.5 | O64: =SUM(C64:N64) -> 37810076
A65: Superannuation expense | B65: =Variance!$C$18 -> 1440000 | C65: =(C63+C64)*$B$31 -> 1487303.5 | D65: =(D63+D64)*$B$31 -> 1762869.4 | E65: =(E63+E64)*$B$31 -> 1898581.2 | F65: =(F63+F64)*$B$31 -> 1380081.9 | G65: =(G63+G64)*$B$31 -> 1318336.8 | H65: =(H63+H64)*$B$31 -> 1420945.3 | I65: =(I63+I64)*$B$31 -> 1402988.6 | J65: =(J63+J64)*$B$31 -> 1451202 | ... N65: =(N63+N64)*$B$31 -> 1501474.4 | O65: =SUM(C65:N65) -> 18102121
A66: Rent and occupancy | B66: =Variance!$C$19 -> 4300000 | C66: =B66*(1+$D$14) -> 4310750 | D66: =C66*(1+$D$14) -> 4321526.9 | E66: =D66*(1+$D$14) -> 4332330.7 | F66: =E66*(1+$D$14) -> 4343161.5 | G66: =F66*(1+$D$14) -> 4354019.4 | H66: =G66*(1+$D$14) -> 4364904.5 | I66: =H66*(1+$D$14) -> 4375816.7 | J66: =I66*(1+$D$14) -> 4386756.3 | ... N66: =M66*(1+$D$14) -> 4430788.6 | O66: =SUM(C66:N66) -> 52446235
A67: Marketing | B67: =Variance!$C$20 -> 3350000 | C67: =C56*$B$29 -> 3495460 | D67: =D56*$B$29 -> 4356904.3 | E67: =E56*$B$29 -> 4779660.1 | F67: =F56*$B$29 -> 3150342.3 | G67: =G56*$B$29 -> 2953719.8 | H67: =H56*$B$29 -> 3272618.5 | I67: =I56*$B$29 -> 3213332.5 | J67: =J56*$B$29 -> 3361594.9 | ... N67: =N56*$B$29 -> 3507336 | O67: =SUM(C67:N67) -> 42549115
A68: IT and software | B68: =Variance!$C$21 -> 780000 | C68: =B68*(1+$D$14) -> 781950 | D68: =C68*(1+$D$14) -> 783904.88 | E68: =D68*(1+$D$14) -> 785864.64 | F68: =E68*(1+$D$14) -> 787829.3 | G68: =F68*(1+$D$14) -> 789798.87 | H68: =G68*(1+$D$14) -> 791773.37 | I68: =H68*(1+$D$14) -> 793752.8 | J68: =I68*(1+$D$14) -> 795737.18 | ... N68: =M68*(1+$D$14) -> 803724.45 | O68: =SUM(C68:N68) -> 9513503
A69: Utilities | B69: =Variance!$C$22 -> 410000 | C69: =B69*(1+$D$14) -> 411025 | D69: =C69*(1+$D$14) -> 412052.56 | E69: =D69*(1+$D$14) -> 413082.69 | F69: =E69*(1+$D$14) -> 414115.4 | G69: =F69*(1+$D$14) -> 415150.69 | H69: =G69*(1+$D$14) -> 416188.57 | I69: =H69*(1+$D$14) -> 417229.04 | J69: =I69*(1+$D$14) -> 418272.11 | ... N69: =M69*(1+$D$14) -> 422470.54 | O69: =SUM(C69:N69) -> 5000687.5
A70: Bank and merchant fees | B70: =Variance!$C$23 -> 690000 | C70: =C56*$B$30 -> 719960.42 | D70: =D56*$B$30 -> 897392.22 | E70: =E56*$B$30 -> 984467.31 | F70: =F56*$B$30 -> 648876.47 | G70: =G56*$B$30 -> 608378.11 | H70: =H56*$B$30 -> 674061.73 | I70: =I56*$B$30 -> 661850.57 | J70: =J56*$B$30 -> 692388.21 | ... N70: =N56*$B$30 -> 722406.53 | O70: =SUM(C70:N70) -> 8763847.5
A71: Other operating expenses | B71: =Variance!$C$24 -> 1050000 | C71: =B71*(1+$D$14) -> 1052625 | D71: =C71*(1+$D$14) -> 1055256.6 | E71: =D71*(1+$D$14) -> 1057894.7 | F71: =E71*(1+$D$14) -> 1060539.4 | G71: =F71*(1+$D$14) -> 1063190.8 | H71: =G71*(1+$D$14) -> 1065848.8 | I71: =H71*(1+$D$14) -> 1068513.4 | J71: =I71*(1+$D$14) -> 1071184.7 | ... N71: =M71*(1+$D$14) -> 1081936.8 | O71: =SUM(C71:N71) -> 12806639
A72: Total operating expenses (before depreciation) | B72: =SUM(B63:B71) -> 24020000 | C72: =SUM(C63:C71) -> 24653270 | D72: =SUM(D63:D71) -> 28280485 | E72: =SUM(E63:E71) -> 30073391 | F72: =SUM(F63:F71) -> 23285629 | G72: =SUM(G63:G71) -> 22488735 | H72: =SUM(H63:H71) -> 23847552 | I72: =SUM(I63:I71) -> 23625055 | ... N72: =SUM(N63:N71) -> 24982424 | O72: =SUM(C72:N72) -> 3.0003315e+08
A73: EBITDA | B73: =B61-B72 -> 4410000 | C73: =C61-C72 -> 5011186.2 | D73: =D61-D72 -> 8694675.4 | E73: =E61-E72 -> 10489516 | F73: =F61-F72 -> 3449962.5 | G73: =G61-G72 -> 2578206.9 | H73: =H61-H72 -> 3925745.2 | I73: =I61-I72 -> 3645106.5 | ... N73: =N61-N72 -> 4782818.8 | O73: =SUM(C73:N73) -> 61062765
A74: EBITDA margin % | B74: =IF(B56=0,0,B73/B56) -> 0.087936191 | C74: =IF(C56=0,0,C73/C56) -> 0.095765719 | D74: =IF(D56=0,0,D73/D56) -> 0.13330586 | E74: =IF(E56=0,0,E73/E56) -> 0.14659943 | F74: =IF(F56=0,0,F73/F56) -> 0.073152724 | G74: =IF(G56=0,0,G73/G56) -> 0.058307221 | H74: =IF(H56=0,0,H73/H56) -> 0.080131006 | I74: =IF(I56=0,0,I73/I56) -> 0.075775433 | ... O74: =IF(O56=0,0,O73/O56) -> 0.095864941
A75: Depreciation | B75: =Variance!$C$27 -> 1650000 | C75: =B75*(1+$D$16) -> 1658250 | D75: =C75*(1+$D$16) -> 1666541.2 | E75: =D75*(1+$D$16) -> 1674874 | F75: =E75*(1+$D$16) -> 1683248.3 | G75: =F75*(1+$D$16) -> 1691664.6 | H75: =G75*(1+$D$16) -> 1700122.9 | I75: =H75*(1+$D$16) -> 1708623.5 | J75: =I75*(1+$D$16) -> 1717166.6 | ... N75: =M75*(1+$D$16) -> 1751768.4 | O75: =SUM(C75:N75) -> 20455446
A76: EBIT | B76: =B73-B75 -> 2760000 | C76: =C73-C75 -> 3352936.2 | D76: =D73-D75 -> 7028134.1 | E76: =E73-E75 -> 8814641.7 | F76: =F73-F75 -> 1766714.2 | G76: =G73-G75 -> 886542.37 | H76: =H73-H75 -> 2225622.3 | I76: =I73-I75 -> 1936483 | ... N76: =N73-N75 -> 3031050.4 | O76: =SUM(C76:N76) -> 40607319
A77: Interest expense | B77: =Variance!$C$29 -> 640000 | C77: =B77 -> 640000 | D77: =C77 -> 640000 | E77: =D77 -> 640000 | F77: =E77 -> 640000 | G77: =F77 -> 640000 | H77: =G77 -> 640000 | I77: =H77 -> 640000 | J77: =I77 -> 640000 | ... N77: =M77 -> 640000 | O77: =SUM(C77:N77) -> 7680000
A78: Net profit before tax | B78: =B76-B77 -> 2120000 | C78: =C76-C77 -> 2712936.2 | D78: =D76-D77 -> 6388134.1 | E78: =E76-E77 -> 8174641.7 | F78: =F76-F77 -> 1126714.2 | G78: =G76-G77 -> 246542.37 | H78: =H76-H77 -> 1585622.3 | I78: =I76-I77 -> 1296483 | ... N78: =N76-N77 -> 2391050.4 | O78: =SUM(C78:N78) -> 32927319
A80: Budget proxy (the Sep-26 budget scaled by seasonality; replace with the approved FY27 monthly budget)
A81: Net sales: budget proxy | B81: =Variance!$D$9 -> 50300000 | C81: =$B$81*C$37 -> 51809000 | D81: =$B$81*D$37 -> 64384000 | E81: =$B$81*E$37 -> 70420000 | F81: =$B$81*F$37 -> 46276000 | G81: =$B$81*G$37 -> 43258000 | H81: =$B$81*H$37 -> 47785000 | I81: =$B$81*I$37 -> 46779000 | J81: =$B$81*J$37 -> 48791000 | ... N81: =$B$81*N$37 -> 50300000 | O81: =SUM(C81:N81) -> 620702000
A82: Gross margin %: budget proxy | B82: =IF(Variance!$D$9=0,0,Variance!$D$14/Variance!$D$9) -> 0.57753479 | C82: =$B$82 -> 0.57753479 | D82: =$B$82 -> 0.57753479 | E82: =$B$82 -> 0.57753479 | F82: =$B$82 -> 0.57753479 | G82: =$B$82 -> 0.57753479 | H82: =$B$82 -> 0.57753479 | I82: =$B$82 -> 0.57753479 | J82: =$B$82 -> 0.57753479 | ... N82: =$B$82 -> 0.57753479 | O82: =IF(O81=0,0,O83/O81) -> 0.57753479
A83: Gross profit: budget proxy | B83: =B81*B82 -> 29050000 | C83: =C81*C82 -> 29921500 | D83: =D81*D82 -> 37184000 | E83: =E81*E82 -> 40670000 | F83: =F81*F82 -> 26726000 | G83: =G81*G82 -> 24983000 | H83: =H81*H82 -> 27597500 | I83: =I81*I82 -> 27016500 | ... N83: =N81*N82 -> 29050000 | O83: =SUM(C83:N83) -> 358477000
A84: Operating expenses before depreciation: budget proxy | B84: =Variance!$D$25 -> 23230000 | C84: =$B$84*($B$32*C$37+(1-$B$32)) -> 23631820 | D84: =$B$84*($B$32*D$37+(1-$B$32)) -> 26980320 | E84: =$B$84*($B$32*E$37+(1-$B$32)) -> 28587600 | F84: =$B$84*($B$32*F$37+(1-$B$32)) -> 22158480 | G84: =$B$84*($B$32*G$37+(1-$B$32)) -> 21354840 | H84: =$B$84*($B$32*H$37+(1-$B$32)) -> 22560300 | I84: =$B$84*($B$32*I$37+(1-$B$32)) -> 22292420 | J84: =$B$84*($B$32*J$37+(1-$B$32)) -> 22828180 | ... N84: =$B$84*($B$32*N$37+(1-$B$32)) -> 23230000 | O84: =SUM(C84:N84) -> 283313960
A85: EBITDA: budget proxy | B85: =B83-B84 -> 5820000 | C85: =C83-C84 -> 6289680 | D85: =D83-D84 -> 10203680 | E85: =E83-E84 -> 12082400 | F85: =F83-F84 -> 4567520 | G85: =G83-G84 -> 3628160 | H85: =H83-H84 -> 5037200 | I85: =I83-I84 -> 4724080 | ... N85: =N83-N84 -> 5820000 | O85: =SUM(C85:N85) -> 75163040
A86: EBITDA: forecast | B86: =B73 -> 4410000 | C86: =C73 -> 5011186.2 | D86: =D73 -> 8694675.4 | E86: =E73 -> 10489516 | F86: =F73 -> 3449962.5 | G86: =G73 -> 2578206.9 | H86: =H73 -> 3925745.2 | I86: =I73 -> 3645106.5 | ... N86: =N73 -> 4782818.8 | O86: =SUM(C86:N86) -> 61062765
A87: Forecast EBITDA vs budget proxy: favourable / (unfavourable) | B87: =B86-B85 -> -1410000 | C87: =C86-C85 -> -1278493.8 | D87: =D86-D85 -> -1509004.6 | E87: =E86-E85 -> -1592884.4 | F87: =F86-F85 -> -1117557.5 | G87: =G86-G85 -> -1049953.1 | H87: =H86-H85 -> -1111454.8 | I87: =I86-I85 -> -1078973.5 | ... N87: =N86-N85 -> -1037181.2 | O87: =SUM(C87:N87) -> -14100275
A89: D. EBITDA bridge: budget proxy to forecast (12 months)
A90: Step | B90: Amount ($)
A91: Budget proxy EBITDA | B91: =O85 -> 75163040
A92: Net sales volume and mix (at budget gross margin %) | B92: =(O56-O81)*O82 -> 9393370.8
A93: Gross margin rate (forecast vs budget %) | B93: =O56*(O62-O82) -> -6774451.3
A94: Operating expenses (higher cost is unfavourable) | B94: =-(O72-O84) -> -16719194
A95: Forecast EBITDA | B95: =SUM(B91:B94) -> 61062765
A97: E. Model checks
A98: Check | B98: Difference | C98: Status
A99: Sep-26 column agrees to Variance tab: net profit before tax | B99: =B78-Variance!$C$30 -> 0 | C99: =IF(ABS(B99)<=Inputs!$C$12,"PASS","FAIL") -> PASS
A100: Sep-26 column agrees to Variance tab: EBITDA | B100: =B73-Variance!$C$26 -> 0 | C100: =IF(ABS(B100)<=Inputs!$C$12,"PASS","FAIL") -> PASS
A101: EBITDA bridge agrees to forecast EBITDA | B101: =B95-O73 -> 0 | C101: =IF(ABS(B101)<=Inputs!$C$12,"PASS","FAIL") -> PASS
A102: 12-month NPBT equals the sum of monthly NPBT | B102: =O78-SUM(C78:N78) -> 0 | C102: =IF(ABS(B102)<=Inputs!$C$12,"PASS","FAIL") -> PASS
A103: Overall forecast status | C103: =IF(COUNTIF(C99:C102,"FAIL")=0,"ALL PASS","FAIL") -> ALL PASS
A105: Notes and assumptions
A106: 1. The Sep-26 column links to the closed actuals on the Variance tab. Forecast months run Oct-26 to Sep-27 and roll forward each close.
A107: 2. Sales = traffic x conversion x basket (stores) and sessions x conversion x AOV (online). Calibration drivers are simulated; replace with footfall and web analytics.
A108: 3. Variable costs (COGS, freight, shrinkage, store wages, marketing, merchant fees) follow net sales at Sep-26 ratios; fixed costs inflate monthly; interest is held flat.
...

Sheet Automation
A1: Process Automation Log
A2: =Inputs!$C$3 -> Specialty retailer (simulated, Adairs-style)
A3: Period end | B3: =Inputs!$C$5 -> 46295
A4: Status: built (automation 1 complete; backlog identified). Results below are from running bank_rec_automation.py on the Sep-26 sample files.
A6: 1. Automation: bank reconciliation matching and exception report
A7: Item | B7: Detail
A8: Script | B8: bank_rec_automation.py (Python 3, standard library only). Sample inputs: sample_bank_statement.csv, sample_gl_cash_book.csv.
A9: Run | B9: python bank_rec_automation.py sample_bank_statement.csv sample_gl_cash_book.csv --bank-balance 6638170 --gl-balance 7190000 --period-end 2026-09-30
A10: Rule 1 | B10: Match bank to GL lines one-to-one on exact amount (to the cent) and dates within +/- 3 days (adjustable).
A11: Rule 2 | B11: Where several candidates qualify, the closest date wins; ties go to the earliest line.
A12: Rule 3 | B12: Unmatched bank line = GL adjustment (journal required). Unmatched GL line = timing item, flagged AGED beyond the Inputs ageing threshold.
A13: Proof | B13: Adjusted GL = GL + unmatched bank lines. Adjusted bank = bank + unmatched GL lines. The script exits non-zero unless they agree.
A14: Output | B14: exceptions_report.csv with source, ref, date, amount, classification, days open, aged flag and suggested action.
A16: 2. Script run vs Rec_Bank tab
A17: Ref | B17: Metric | C17: Per script run | D17: Per Rec_Bank ($) | E17: Difference | F17: Status
A18: R1 | B18: Bank statement lines processed | C18: 27
A19: R2 | B19: GL cash book lines processed | C19: 29
A20: R3 | B20: Matched pairs | C20: 26
A21: R4 | B21: GL adjustments (unmatched bank lines) ($) | C21: -38410 | D21: =Rec_Bank!$D$11 -> -38410 | E21: =C21-D21 -> 0 | F21: =IF(ABS(E21)<=Inputs!$C$12,"TIES","INVESTIGATE") -> TIES
A22: R5 | B22: Timing items (unmatched GL lines) ($) | C22: 513420 | D22: =Rec_Bank!$D$15 -> 513420 | E22: =C22-D22 -> 0 | F22: =IF(ABS(E22)<=Inputs!$C$12,"TIES","INVESTIGATE") -> TIES
A23: R6 | B23: Adjusted GL balance ($) | C23: 7151590 | D23: =Rec_Bank!$D$12 -> 7151590 | E23: =C23-D23 -> 0 | F23: =IF(ABS(E23)<=Inputs!$C$12,"TIES","INVESTIGATE") -> TIES
A24: R7 | B24: Adjusted bank balance ($) | C24: 7151590 | D24: =Rec_Bank!$D$16 -> 7151590 | E24: =C24-D24 -> 0 | F24: =IF(ABS(E24)<=Inputs!$C$12,"TIES","INVESTIGATE") -> TIES
A25: R8 | B25: Unreconciled difference ($) | C25: 0 | D25: =Rec_Bank!$D$18 -> 0 | E25: =C25-D25 -> 0 | F25: =IF(ABS(E25)<=Inputs!$C$12,"TIES","INVESTIGATE") -> TIES
A26: R9 | B26: Aged timing items (count) | C26: 1 | D26: =Rec_Bank!$D$19 -> 1 | E26: =C26-D26 -> 0 | F26: =IF(ABS(E26)<=Inputs!$C$12,"TIES","INVESTIGATE") -> TIES
A27: Script figures are hardcoded from the run on 9-Oct-2026 (blue). Re-run the script and update column C each close.
A29: 3. Exception report tie-out to Rec_Bank reconciling items
A30: Script ref | B30: Description (per exception report) | C30: Classification | D30: Script amount ($) | E30: Rec_Bank ref | F30: Rec_Bank amount ($) | G30: Difference | H30: Status
A31: BS-026 | B31: Merchant fees - September (bank debit) | C31: GL adjustment | D31: -38410 | E31: =Rec_Bank!$A$22 -> BNK-01 | F31: =Rec_Bank!$D$22 -> -38410 | G31: =D31-F31 -> 0 | H31: =IF(ABS(G31)<=Inputs!$C$12,"TIES","INVESTIGATE") -> TIES
A32: CB-029 | B32: Card settlement trading 30 Sep (banks 1 Oct) | C32: Timing | D32: 1420350 | E32: =Rec_Bank!$A$23 -> BNK-02 | F32: =Rec_Bank!$D$23 -> 1420350 | G32: =D32-F32 -> 0 | H32: =IF(ABS(G32)<=Inputs!$C$12,"TIES","INVESTIGATE") -> TIES
A33: CB-026 | B33: Supplier EFT batch released 29 Sep (clears 1 Oct) | C33: Timing | D33: -845200 | E33: =Rec_Bank!$A$24 -> BNK-03 | F33: =Rec_Bank!$D$24 -> -845200 | G33: =D33-F33 -> 0 | H33: =IF(ABS(G33)<=Inputs!$C$12,"TIES","INVESTIGATE") -> TIES
A34: CB-001 | B34: Unpresented refund payments (brought forward), 34 days | C34: Timing - AGED | D34: -61730 | E34: =Rec_Bank!$A$25 -> BNK-04 | F34: =Rec_Bank!$D$25 -> -61730 | G34: =D34-F34 -> 0 | H34: =IF(ABS(G34)<=Inputs!$C$12,"TIES","INVESTIGATE") -> TIES
A35: Total | D35: =SUM(D31:D34) -> 475010 | F35: =SUM(F31:F34) -> 475010 | G35: =D35-F35 -> 0
A37: 4. Time saved (before / after)
A38: Ref | B38: Item | C38: Value | D38: Basis
A39: T1 | B39: Lines to review (bank + GL) | C39: =C18+C19 -> 56 | D39: From section 2
A40: T2 | B40: Manual: seconds per line to tick and match | C40: 40 | D40: ESTIMATE. Replace with your own stopwatch timing.
A41: T3 | B41: Manual: minutes to prepare schedule and investigate items | C41: 15 | D41: ESTIMATE
A42: T4 | B42: Manual: total minutes | C42: =C39*C40/60+C41 -> 52.333333 | D42: T1 x T2 / 60 + T3
A43: T5 | B43: Automated: script runtime (seconds) | C43: 0.001 | D43: MEASURED on the sample run (reported by the script)
A44: T6 | B44: Automated: minutes to load files and review exceptions | C44: 14 | D44: ESTIMATE: 2 min to load + about 3 min per exception
A45: T7 | B45: Automated: total minutes | C45: =C43/60+C44 -> 14.000017 | D45: T5 / 60 + T6
A46: T8 | B46: Minutes saved per close | C46: =C42-C45 -> 38.333317 | D46: T4 less T7
A47: T9 | B47: Time saved (%) | C47: =IF(C42=0,0,C46/C42) -> 0.73248376
A48: T10 | B48: Hours saved per year (12 closes) | C48: =C46*12/60 -> 7.6666633 | D48: Single bank account only; scales with accounts and line volume
A49: Matching effort is the part that scales: manual time grows with line count while review time grows only with exceptions.
A51: 5. Automation backlog identified during the Sep-26 close
A52: # | B52: Opportunity | C52: Close calendar task | D52: Approach | E52: Effort | F52: Status | G52: Priority | H52: Expected benefit
A53: 1 | B53: Bank reconciliation matching and exception report | C53: 7. Bank reconciliation prepared | D53: Python matcher (built) | E53: Low | F53: Done | G53: High | H53: Removes line-by-line ticking; exceptions feed Rec_Bank directly
A54: 2 | B54: Journal upload file from reconciliation GL adjustments | C54: 15. Post journals identified in reconciliations | D54: Generate balanced ERP journal CSV from "GL adjustment" lines | E54: Low | F54: Planned | G54: High | H54: Cuts rekeying errors; balance check before upload
A55: 3 | B55: Flux report with threshold flags and commentary prompts | C55: 17. P&L flux analysis | D55: Python or Power Query on TB export using Inputs thresholds | E55: Medium | F55: Planned | G55: High | H55: Same-day flux pack; commentary drafted against drivers
A56: 4 | B56: AP and AR subledger to GL matching | C56: 8-9. AP and AR reconciliations | D56: Extend matcher to invoice reference keys | E56: Medium | F56: Planned | G56: Medium | H56: Surfaces interface failures such as AP-01 and AR-01
A57: 5 | B57: BAS data extract and GST coding exceptions | C57: 12. GST clearing; 22. BAS / IAS | D57: Power Query on GL by tax code, flag uncoded GST | E57: Medium | F57: Planned | G57: Medium | H57: Earlier detection of items like GST-01
A58: 6 | B58: Close calendar status reminders | C58: All tasks | D58: Power Automate from status column | E58: Low | F58: Planned | G58: Low | H58: Fewer follow-ups on overdue tasks
A60: Backlog items completed | C60: =COUNTIF(F53:F58,"Done") -> 1 | D60: =COUNTA(B53:B58) -> 6
A62: 6. Controls and limitations
A63: 1. | B63: Deterministic: the same inputs always give the same output, so the exception report is reproducible for audit.
A64: 2. | B64: Exact-amount matching only. Many-to-one items (for example one bank deposit covering several GL receipts) fall into exceptions and need manual review.
A65: 3. | B65: Matching is greedy by GL date order. If two same-amount lines compete, the closest date wins; review ties in the report.
A66: 4. | B66: The proof (adjusted GL = adjusted bank) guards against missed or duplicated lines. A non-zero difference stops the run with a non-zero exit code.
A67: 5. | B67: Sample data is simulated. With real bank files, keep extracts in a controlled folder and do not commit them to a public repository.
